[{"type":"3","number":"1","header":"\u003cdiv class\u003d\"qustion\"\u003e\u003cdiv class\u003d\"field-number\"\u003e  1 \u003c/div\u003e \u003cdiv class\u003d\"field-image\"\u003e  \u003cimg src\u003d\"!image_source!\" alt\u003d\"\"\u003e \u003c/div\u003e \u003cdiv class\u003d\"field-audio\"\u003e   \u003c/div\u003e \u003cdiv class\u003d\"text-center field-subject ans-hide\"\u003e  \u003cp class\u003d\"pinyin\"\u003e青少年的兴趣爱好若能及早得到培养，就能表现出某一方面的才能。老师根据学生的爱好，有意识地加以引导，就会使学生在自己爱好的活动中发展特长、增长聪明才智，进而具有发现问题、分析问题、解决问题的能力。\u003c/p\u003e \u003c/div\u003e\u003c/div\u003e","body":[{"number":"1","value":{"A":"每个孩子都有自己的特长","B":"好老师要能发现学生的问题","C":"老师要善于帮学生解决问题","D":"老师要根据学生的特长加以引导"}}],"category":"NGHE"},{"type":"3","number":"2","header":"\u003cdiv class\u003d\"qustion\"\u003e\u003cdiv class\u003d\"field-number\"\u003e  1 \u003c/div\u003e \u003cdiv class\u003d\"field-image\"\u003e  \u003cimg src\u003d\"!image_source!\" alt\u003d\"\"\u003e \u003c/div\u003e \u003cdiv class\u003d\"field-audio\"\u003e  \u003caudio controls\u003d\"\" controlsList\u003d\"nodownload\"\u003e \r\n  \u003csource src\u003d\"http://localhost:8081/audios/BT/6/19 - Giáo trình chuẩn HSK 6 - SBT - question 1.mp3\" type\u003d\"audio/mpeg\"\u003e Your browser does not support the audio element. \r\n \u003c/audio\u003e \u003cdiv class\u003d\"btn-slide\"\u003e   \u003cdiv class\u003d\"btn\" style\u003d\"    background-color: inherit;    padding-top: 0px;    \"\u003e \u003cspan onclick\u003d\"previous(this)\" type\u003d\"button\"\u003e\u003ci class\u003d\"fa fa-backward\" style\u003d\"    color: black;\"\u003e\u003c/i\u003e\u003c/span\u003e   \u003c/div\u003e   \u003cdiv class\u003d\"btn\" style\u003d\"    background-color: inherit;    padding-right: 30px;    padding-top: 0px;    padding-bottom: 10px;    padding-left: 30px;    \"\u003e \u003cspan onclick\u003d\"next(this)\" type\u003d\"button\"\u003e\u003ci class\u003d\"fa fa-forward\" style\u003d\"    color: black;\"\u003e\u003c/i\u003e\u003c/span\u003e   \u003c/div\u003e  \u003c/div\u003e  \u003cbr\u003e  \u003c/div\u003e \u003cdiv class\u003d\"text-center field-subject ans-hide\"\u003e  \u003cp class\u003d\"pinyin\"\u003e7月份新疆出现异常高温天气，大部分地区最高气温在35摄氏度以上,一些地区的最高气温为40摄氏度以上。首府乌鲁木齐14日最高气温达到40.6摄氏度,突破近30年来最高气温历史极值,吐鲁番地区最高气温达到46.2摄氏度。\u003c/p\u003e \u003c/div\u003e\u003c/div\u003e","body":[{"number":"2","value":{"A":"乌鲁木齐是新疆的首府","B":"在新疆40℃高温很普遍","C":"7月份新疆的天气反复无常","D":"乌鲁木齐的气温高于吐鲁番"}}],"category":"NGHE"},{"type":"3","number":"3","header":"\u003cdiv class\u003d\"qustion\"\u003e\u003cdiv class\u003d\"field-number\"\u003e  1 \u003c/div\u003e \u003cdiv class\u003d\"field-image\"\u003e  \u003cimg src\u003d\"!image_source!\" alt\u003d\"\"\u003e \u003c/div\u003e \u003cdiv class\u003d\"field-audio\"\u003e  \u003caudio controls\u003d\"\" controlsList\u003d\"nodownload\"\u003e \r\n  \u003csource src\u003d\"http://localhost:8081/audios/BT/6/19 - Giáo trình chuẩn HSK 6 - SBT - question 2.mp3\" type\u003d\"audio/mpeg\"\u003e Your browser does not support the audio element. \r\n \u003c/audio\u003e \u003cdiv class\u003d\"btn-slide\"\u003e   \u003cdiv class\u003d\"btn\" style\u003d\"    background-color: inherit;    padding-top: 0px;    \"\u003e \u003cspan onclick\u003d\"previous(this)\" type\u003d\"button\"\u003e\u003ci class\u003d\"fa fa-backward\" style\u003d\"    color: black;\"\u003e\u003c/i\u003e\u003c/span\u003e   \u003c/div\u003e   \u003cdiv class\u003d\"btn\" style\u003d\"    background-color: inherit;    padding-right: 30px;    padding-top: 0px;    padding-bottom: 10px;    padding-left: 30px;    \"\u003e \u003cspan onclick\u003d\"next(this)\" type\u003d\"button\"\u003e\u003ci class\u003d\"fa fa-forward\" style\u003d\"    color: black;\"\u003e\u003c/i\u003e\u003c/span\u003e   \u003c/div\u003e  \u003c/div\u003e  \u003cbr\u003e  \u003c/div\u003e \u003cdiv class\u003d\"text-center field-subject ans-hide\"\u003e  \u003cp class\u003d\"pinyin\"\u003e随着社会的发展，新事物、新概念不断出现，这些都会向交际提出新的要求，我们翻阅解放前的书报杂志，就会感到有些词语很陌生，有些格式很不习惯。社会的发展变迁必然会在语言的词汇里留下印记。\u003c/p\u003e \u003c/div\u003e\u003c/div\u003e","body":[{"number":"3","value":{"A":"每个人都向交际提出新要求","B":"历史会记录社会的发展变化","C":"语言会随着社会的变化而变化","D":"书面语和口语有许多不同之处"}}],"category":"NGHE"},{"type":"3","number":"4","header":"\u003cdiv class\u003d\"qustion\"\u003e\u003cdiv class\u003d\"field-number\"\u003e  1 \u003c/div\u003e \u003cdiv class\u003d\"field-image\"\u003e  \u003cimg src\u003d\"!image_source!\" alt\u003d\"\"\u003e \u003c/div\u003e \u003cdiv class\u003d\"field-audio\"\u003e  \u003caudio controls\u003d\"\" controlsList\u003d\"nodownload\"\u003e \r\n  \u003csource src\u003d\"http://localhost:8081/audios/BT/6/19 - Giáo trình chuẩn HSK 6 - SBT - question 3.mp3\" type\u003d\"audio/mpeg\"\u003e Your browser does not support the audio element. \r\n \u003c/audio\u003e \u003cdiv class\u003d\"btn-slide\"\u003e   \u003cdiv class\u003d\"btn\" style\u003d\"    background-color: inherit;    padding-top: 0px;    \"\u003e \u003cspan onclick\u003d\"previous(this)\" type\u003d\"button\"\u003e\u003ci class\u003d\"fa fa-backward\" style\u003d\"    color: black;\"\u003e\u003c/i\u003e\u003c/span\u003e   \u003c/div\u003e   \u003cdiv class\u003d\"btn\" style\u003d\"    background-color: inherit;    padding-right: 30px;    padding-top: 0px;    padding-bottom: 10px;    padding-left: 30px;    \"\u003e \u003cspan onclick\u003d\"next(this)\" type\u003d\"button\"\u003e\u003ci class\u003d\"fa fa-forward\" style\u003d\"    color: black;\"\u003e\u003c/i\u003e\u003c/span\u003e   \u003c/div\u003e  \u003c/div\u003e  \u003cbr\u003e  \u003c/div\u003e \u003cdiv class\u003d\"text-center field-subject ans-hide\"\u003e  \u003cp class\u003d\"pinyin\"\u003e今年读到了新近出版的“经济新观察”丛书中的林行止系列和熊秉元系列。林行止读书甚广，读他的文章犹如进入阿里巴巴的山洞，美不胜收。熊秉元善于从一些日常小事中总结出经济学精神，读来有滋有味。\u003c/p\u003e \u003c/div\u003e\u003c/div\u003e","body":[{"number":"4","value":{"A":"林行止、熊秉元都是小说作家","B":"林行止的书介绍了很多旅游景点","C":"熊秉元的书内容常涉及餐饮美味","D":"“经济新观察”是一套经济学书籍"}}],"category":"NGHE"},{"type":"3","number":"5","header":"\u003cdiv class\u003d\"qustion\"\u003e\u003cdiv class\u003d\"field-number\"\u003e  1 \u003c/div\u003e \u003cdiv class\u003d\"field-image\"\u003e  \u003cimg src\u003d\"!image_source!\" alt\u003d\"\"\u003e \u003c/div\u003e \u003cdiv class\u003d\"field-audio\"\u003e  \u003caudio controls\u003d\"\" controlsList\u003d\"nodownload\"\u003e \r\n  \u003csource src\u003d\"http://localhost:8081/audios/BT/6/19 - Giáo trình chuẩn HSK 6 - SBT - question 4.mp3\" type\u003d\"audio/mpeg\"\u003e Your browser does not support the audio element. \r\n \u003c/audio\u003e \u003cdiv class\u003d\"btn-slide\"\u003e   \u003cdiv class\u003d\"btn\" style\u003d\"    background-color: inherit;    padding-top: 0px;    \"\u003e \u003cspan onclick\u003d\"previous(this)\" type\u003d\"button\"\u003e\u003ci class\u003d\"fa fa-backward\" style\u003d\"    color: black;\"\u003e\u003c/i\u003e\u003c/span\u003e   \u003c/div\u003e   \u003cdiv class\u003d\"btn\" style\u003d\"    background-color: inherit;    padding-right: 30px;    padding-top: 0px;    padding-bottom: 10px;    padding-left: 30px;    \"\u003e \u003cspan onclick\u003d\"next(this)\" type\u003d\"button\"\u003e\u003ci class\u003d\"fa fa-forward\" style\u003d\"    color: black;\"\u003e\u003c/i\u003e\u003c/span\u003e   \u003c/div\u003e  \u003c/div\u003e  \u003cbr\u003e  \u003c/div\u003e \u003cdiv class\u003d\"text-center field-subject ans-hide\"\u003e  \u003cp class\u003d\"pinyin\"\u003e从渔猎到农业，人类社会先是出现了半永久性的农牧业村舍，之后有了定居的村庄。但这种状况也未能持久，一旦地力衰竭或人口增长过快，整个村舍就要迁移，或分裂成较小的组团，寻找新的住地，以保证足够的耕地。\u003c/p\u003e \u003c/div\u003e\u003c/div\u003e","body":[{"number":"5","value":{"A":"人类的定居促进了人口的增长","B":"农业的发展也促进了渔猎文明","C":"人口迁移是为了解决耕地问题","D":"人类定居从渔猎时期就开始了"}}],"category":"NGHE"},{"type":"2","number":"6-10","header":"女：听说你是个美食家？\n男：美食家谈不上，只能说我是一个对美食没有抵抗力的人，我的优点就是不挑食。\n女：你认为什么是美食？\n男：美食是可以让你身心愉悦的妙药。\n女：能说得具体点儿吗？\n男：在心情好的时候、疲惫的时候或是悠闲的时候，享受一顿可口的饭菜，那一定是最幸福的时刻。\n女：看来吃什么在其次，只要能让你有愉快的感受，什么都是美食？\n男：可以这么说。可是也有例外，对于我来讲，新疆的饭菜都是美味佳肴，因为我是新疆人嘛。还有，南京算是我的第二故乡，我对南京美食也是爱得不得了呀。\n女：对吃你有什么感悟？\n男：俗话说“民以食为天”，吃对于每个人来讲都是生存本能。可是，众所周知，吃给予我们的远不止于此，我更在意的是与家人、友人在“吃”的那个时刻围坐在一起，暂时放下忙碌的工作，忘掉这样那样的烦恼，享受片刻难得的悠闲。\n女：平常你下厨吗？\n男：以前经常下厨，现在因为工作的关系，下厨少了。其实我很享受烹饪的过程，能亲手为家人准备一桌饭菜，是一件非常幸福的事情。虽然做不出用料复杂、精致无比的饭菜，色香味俱佳还是没有问题的。\n女：讲个关于你的吃的故事吧？\n男：要说就说与拍戏有关的吃，那是在拍摄《特种兵》的时候。这部戏主要讲的是女特种兵的故事，拍戏强度很高，体力消耗特别大。我们的阵容中女演员居多，女孩子嘛，本来就喜欢吃一些零食和水果之类的东西，可是在戏里我是教官，总操练她们，尤其不允许她们吃零食。每天女演员们顶着烈日做体能训练，还得忍受我的“训斥”。直到今天，我心里还对她们抱有歉意，觉得当时我丧失了一个男子汉对女士们应有的同情心。\n","body":[{"number":"6","header":"6. 在吃的问题上，男的是个什么样的人？\n","value":{"A":"没有不爱吃的食物","B":"对美食的要求很高","C":"只吃自己喜爱的食物","D":"对美食有奇特的标准"}},{"number":"7","header":"7. 关于男的眼中的美食，下列哪项正确？\n\u003caudio controls\u003d\"\" controlsList\u003d\"nodownload\"\u003e \r\n  \u003csource src\u003d\"http://localhost:8081/audios/BT/6/19 - Giáo trình chuẩn HSK 6 - SBT - question 6.mp3\" type\u003d\"audio/mpeg\"\u003e Your browser does not support the audio element. \r\n \u003c/audio\u003e \u003cdiv class\u003d\"btn-slide\"\u003e   \u003cdiv class\u003d\"btn\" style\u003d\"    background-color: inherit;    padding-top: 0px;    \"\u003e \u003cspan onclick\u003d\"previous(this)\" type\u003d\"button\"\u003e\u003ci class\u003d\"fa fa-backward\" style\u003d\"    color: black;\"\u003e\u003c/i\u003e\u003c/span\u003e   \u003c/div\u003e   \u003cdiv class\u003d\"btn\" style\u003d\"    background-color: inherit;    padding-right: 30px;    padding-top: 0px;    padding-bottom: 10px;    padding-left: 30px;    \"\u003e \u003cspan onclick\u003d\"next(this)\" type\u003d\"button\"\u003e\u003ci class\u003d\"fa fa-forward\" style\u003d\"    color: black;\"\u003e\u003c/i\u003e\u003c/span\u003e   \u003c/div\u003e  \u003c/div\u003e  \u003cbr\u003e ","value":{"A":"美食是可以治病的","B":"口味独特的是美食","C":"家乡的食物是美食","D":"饿了吃什么都是美食"}},{"number":"8","header":"8. 对于吃，男的有什么感悟？\n\u003caudio controls\u003d\"\" controlsList\u003d\"nodownload\"\u003e \r\n  \u003csource src\u003d\"http://localhost:8081/audios/BT/6/19 - Giáo trình chuẩn HSK 6 - SBT - question 7.mp3\" type\u003d\"audio/mpeg\"\u003e Your browser does not support the audio element. \r\n \u003c/audio\u003e \u003cdiv class\u003d\"btn-slide\"\u003e   \u003cdiv class\u003d\"btn\" style\u003d\"    background-color: inherit;    padding-top: 0px;    \"\u003e \u003cspan onclick\u003d\"previous(this)\" type\u003d\"button\"\u003e\u003ci class\u003d\"fa fa-backward\" style\u003d\"    color: black;\"\u003e\u003c/i\u003e\u003c/span\u003e   \u003c/div\u003e   \u003cdiv class\u003d\"btn\" style\u003d\"    background-color: inherit;    padding-right: 30px;    padding-top: 0px;    padding-bottom: 10px;    padding-left: 30px;    \"\u003e \u003cspan onclick\u003d\"next(this)\" type\u003d\"button\"\u003e\u003ci class\u003d\"fa fa-forward\" style\u003d\"    color: black;\"\u003e\u003c/i\u003e\u003c/span\u003e   \u003c/div\u003e  \u003c/div\u003e  \u003cbr\u003e ","value":{"A":"吃是人生头等大事","B":"吃能解决生存问题","C":"吃能提供营养，保证健康","D":"可以和亲友一起享受悠闲"}},{"number":"9","header":"9. 在做饭的问题上，下列哪项正确？\n\u003caudio controls\u003d\"\" controlsList\u003d\"nodownload\"\u003e \r\n  \u003csource src\u003d\"http://localhost:8081/audios/BT/6/19 - Giáo trình chuẩn HSK 6 - SBT - question 8.mp3\" type\u003d\"audio/mpeg\"\u003e Your browser does not support the audio element. \r\n \u003c/audio\u003e \u003cdiv class\u003d\"btn-slide\"\u003e   \u003cdiv class\u003d\"btn\" style\u003d\"    background-color: inherit;    padding-top: 0px;    \"\u003e \u003cspan onclick\u003d\"previous(this)\" type\u003d\"button\"\u003e\u003ci class\u003d\"fa fa-backward\" style\u003d\"    color: black;\"\u003e\u003c/i\u003e\u003c/span\u003e   \u003c/div\u003e   \u003cdiv class\u003d\"btn\" style\u003d\"    background-color: inherit;    padding-right: 30px;    padding-top: 0px;    padding-bottom: 10px;    padding-left: 30px;    \"\u003e \u003cspan onclick\u003d\"next(this)\" type\u003d\"button\"\u003e\u003ci class\u003d\"fa fa-forward\" style\u003d\"    color: black;\"\u003e\u003c/i\u003e\u003c/span\u003e   \u003c/div\u003e  \u003c/div\u003e  \u003cbr\u003e ","value":{"A":"男的历来就不愿意做饭","B":"男的太忙，没学过做饭","C":"男的做饭手艺相当不错","D":"男的做饭非常讲究用料"}},{"number":"10","header":"10.关于吃的故事，下列哪项正确？\u003caudio controls\u003d\"\" controlsList\u003d\"nodownload\"\u003e \r\n  \u003csource src\u003d\"http://localhost:8081/audios/BT/6/19 - Giáo trình chuẩn HSK 6 - SBT - question 9.mp3\" type\u003d\"audio/mpeg\"\u003e Your browser does not support the audio element. \r\n \u003c/audio\u003e \u003cdiv class\u003d\"btn-slide\"\u003e   \u003cdiv class\u003d\"btn\" style\u003d\"    background-color: inherit;    padding-top: 0px;    \"\u003e \u003cspan onclick\u003d\"previous(this)\" type\u003d\"button\"\u003e\u003ci class\u003d\"fa fa-backward\" style\u003d\"    color: black;\"\u003e\u003c/i\u003e\u003c/span\u003e   \u003c/div\u003e   \u003cdiv class\u003d\"btn\" style\u003d\"    background-color: inherit;    padding-right: 30px;    padding-top: 0px;    padding-bottom: 10px;    padding-left: 30px;    \"\u003e \u003cspan onclick\u003d\"next(this)\" type\u003d\"button\"\u003e\u003ci class\u003d\"fa fa-forward\" style\u003d\"    color: black;\"\u003e\u003c/i\u003e\u003c/span\u003e   \u003c/div\u003e  \u003c/div\u003e  \u003cbr\u003e ","value":{"A":"男的拍戏时经常吃零食","B":"女演员怕胖不敢吃零食","C":"男的看不惯女演员老吃零食","D":"戏中男的不让女演员吃零食"}}],"category":"NGHE"},{"type":"2","number":"11-13","header":"第 11-13 题是根据下面一段话：\n传统密码的缺陷是显而易见的，简单的密码依然是大多数人保护个人隐私的最常见方式。以人体生物特征作为密码，真的可以变为现实吗？回答是肯定的，距离我们越来越近的“眼泪密码”便是如此。由于眼泪作用于角膜的结果无法被复制，因此“眼泪密码”的安全性有了质的提升。\n“眼泪密码”之所以保密性强，是因为每个人的角膜都有独特的图像，扫描仪可据此甄别不同的人。如果黑客偷取并使用某人上次使用过的数据，机器会认定其无效，因为它“懂得”每次扫描结果都应该有细微的变化。这是因为，角膜表面因有泪水而湿润，因此数据是实时改变的。\n还有科学家在探索声音密码，也有银行推出指纹密码。不过，生物密码技术目前并不完全成熟，假如一个人的手指肿了，那么机器则无法识别出指纹密码。\n","body":[{"number":"11","header":"11.关于传统密码，可以知道什么？\n","value":{"A":"缺点非常明显","B":"简单、可靠、易操作","C":"被黑客偷取后无法使用","D":"比人体生物密码更安全"}},{"number":"12","header":"12.关于眼泪密码，可以知道什么？\n\u003caudio controls\u003d\"\" controlsList\u003d\"nodownload\"\u003e \r\n  \u003csource src\u003d\"http://localhost:8081/audios/BT/6/19 - Giáo trình chuẩn HSK 6 - SBT - question 11.mp3\" type\u003d\"audio/mpeg\"\u003e Your browser does not support the audio element. \r\n \u003c/audio\u003e \u003cdiv class\u003d\"btn-slide\"\u003e   \u003cdiv class\u003d\"btn\" style\u003d\"    background-color: inherit;    padding-top: 0px;    \"\u003e \u003cspan onclick\u003d\"previous(this)\" type\u003d\"button\"\u003e\u003ci class\u003d\"fa fa-backward\" style\u003d\"    color: black;\"\u003e\u003c/i\u003e\u003c/span\u003e   \u003c/div\u003e   \u003cdiv class\u003d\"btn\" style\u003d\"    background-color: inherit;    padding-right: 30px;    padding-top: 0px;    padding-bottom: 10px;    padding-left: 30px;    \"\u003e \u003cspan onclick\u003d\"next(this)\" type\u003d\"button\"\u003e\u003ci class\u003d\"fa fa-forward\" style\u003d\"    color: black;\"\u003e\u003c/i\u003e\u003c/span\u003e   \u003c/div\u003e  \u003c/div\u003e  \u003cbr\u003e ","value":{"A":"安全性有待提升","B":"可复制性差一些","C":"数据会实时改变","D":"黑客破解很容易"}},{"number":"13","header":"13.目前已在银行使用的生物密码是哪一种？\u003caudio controls\u003d\"\" controlsList\u003d\"nodownload\"\u003e \r\n  \u003csource src\u003d\"http://localhost:8081/audios/BT/6/19 - Giáo trình chuẩn HSK 6 - SBT - question 12.mp3\" type\u003d\"audio/mpeg\"\u003e Your browser does not support the audio element. \r\n \u003c/audio\u003e \u003cdiv class\u003d\"btn-slide\"\u003e   \u003cdiv class\u003d\"btn\" style\u003d\"    background-color: inherit;    padding-top: 0px;    \"\u003e \u003cspan onclick\u003d\"previous(this)\" type\u003d\"button\"\u003e\u003ci class\u003d\"fa fa-backward\" style\u003d\"    color: black;\"\u003e\u003c/i\u003e\u003c/span\u003e   \u003c/div\u003e   \u003cdiv class\u003d\"btn\" style\u003d\"    background-color: inherit;    padding-right: 30px;    padding-top: 0px;    padding-bottom: 10px;    padding-left: 30px;    \"\u003e \u003cspan onclick\u003d\"next(this)\" type\u003d\"button\"\u003e\u003ci class\u003d\"fa fa-forward\" style\u003d\"    color: black;\"\u003e\u003c/i\u003e\u003c/span\u003e   \u003c/div\u003e  \u003c/div\u003e  \u003cbr\u003e ","value":{"A":"声音密码","B":"眼泪密码","C":"传统密码","D":"指纹密码"}}],"category":"NGHE"},{"type":"2","number":"14-17","header":"第 14-17 题是根据下面一段话：\n蛤蜊，身上长着像树木年轮一样的纹路，每成长一年，它就仔细地划上一道完美的圆圈。科学家们数了又数，身上有一百二十多圈的蛤蜊并不稀少，也就是说这些蛤蜊穿越了一个世纪，又健康快乐地生活了二十多年。目前发现的最高龄的蛤蜊为507 岁。\n想知道蛤蜊长寿的秘诀吗？夏天对许多动物来说都是最享受的季节，它们大口大口地吃东西，以保持正常的新陈代谢；夏季的美食足够丰盛，它们不担心会没有东西可享用。对于蛤蜊来说，夏季是最幸福的季节，它们要繁殖后代，要承担起做父母的责任和义务，它们没有过多的时间去享用美食，它们的生活简单而快乐。冬天到了，宝宝们长大了，爸爸妈妈也自由了。但这时候草木枯萎、万物藏匿，蛤蜊吃不到多少可口的食物。好在它们习惯了节省而优雅的生活，只要有一些东西吃就足够满意和幸福了。\n正是这些高贵的品质保证了蛤蜊的长寿。也许聪明的人类，这时你恍然大悟了吧，我们总能够从蛤蜊身上想到些什么吧！\n","body":[{"number":"14","header":"14.目前发现最长寿的蛤蜊多少岁？\n\u003caudio controls\u003d\"\" controlsList\u003d\"nodownload\"\u003e \r\n  \u003csource src\u003d\"http://localhost:8081/audios/BT/6/19 - Giáo trình chuẩn HSK 6 - SBT - question 13.mp3\" type\u003d\"audio/mpeg\"\u003e Your browser does not support the audio element. \r\n \u003c/audio\u003e \u003cdiv class\u003d\"btn-slide\"\u003e   \u003cdiv class\u003d\"btn\" style\u003d\"    background-color: inherit;    padding-top: 0px;    \"\u003e \u003cspan onclick\u003d\"previous(this)\" type\u003d\"button\"\u003e\u003ci class\u003d\"fa fa-backward\" style\u003d\"    color: black;\"\u003e\u003c/i\u003e\u003c/span\u003e   \u003c/div\u003e   \u003cdiv class\u003d\"btn\" style\u003d\"    background-color: inherit;    padding-right: 30px;    padding-top: 0px;    padding-bottom: 10px;    padding-left: 30px;    \"\u003e \u003cspan onclick\u003d\"next(this)\" type\u003d\"button\"\u003e\u003ci class\u003d\"fa fa-forward\" style\u003d\"    color: black;\"\u003e\u003c/i\u003e\u003c/span\u003e   \u003c/div\u003e  \u003c/div\u003e  \u003cbr\u003e ","value":{"A":"二十几岁","B":"一百多岁","C":"五百多岁","D":"一百二十岁左右"}},{"number":"15","header":"15.对许多动物来说，夏天是个怎样的季节？\n\u003caudio controls\u003d\"\" controlsList\u003d\"nodownload\"\u003e \r\n  \u003csource src\u003d\"http://localhost:8081/audios/BT/6/19 - Giáo trình chuẩn HSK 6 - SBT - question 14.mp3\" type\u003d\"audio/mpeg\"\u003e Your browser does not support the audio element. \r\n \u003c/audio\u003e \u003cdiv class\u003d\"btn-slide\"\u003e   \u003cdiv class\u003d\"btn\" style\u003d\"    background-color: inherit;    padding-top: 0px;    \"\u003e \u003cspan onclick\u003d\"previous(this)\" type\u003d\"button\"\u003e\u003ci class\u003d\"fa fa-backward\" style\u003d\"    color: black;\"\u003e\u003c/i\u003e\u003c/span\u003e   \u003c/div\u003e   \u003cdiv class\u003d\"btn\" style\u003d\"    background-color: inherit;    padding-right: 30px;    padding-top: 0px;    padding-bottom: 10px;    padding-left: 30px;    \"\u003e \u003cspan onclick\u003d\"next(this)\" type\u003d\"button\"\u003e\u003ci class\u003d\"fa fa-forward\" style\u003d\"    color: black;\"\u003e\u003c/i\u003e\u003c/span\u003e   \u003c/div\u003e  \u003c/div\u003e  \u003cbr\u003e ","value":{"A":"生儿育女的季节","B":"尽情吃喝的季节","C":"保养身体的季节","D":"享受自由的季节"}},{"number":"16","header":"16.蛤蜊在什么时候繁育后代？\n\u003caudio controls\u003d\"\" controlsList\u003d\"nodownload\"\u003e \r\n  \u003csource src\u003d\"http://localhost:8081/audios/BT/6/19 - Giáo trình chuẩn HSK 6 - SBT - question 15.mp3\" type\u003d\"audio/mpeg\"\u003e Your browser does not support the audio element. \r\n \u003c/audio\u003e \u003cdiv class\u003d\"btn-slide\"\u003e   \u003cdiv class\u003d\"btn\" style\u003d\"    background-color: inherit;    padding-top: 0px;    \"\u003e \u003cspan onclick\u003d\"previous(this)\" type\u003d\"button\"\u003e\u003ci class\u003d\"fa fa-backward\" style\u003d\"    color: black;\"\u003e\u003c/i\u003e\u003c/span\u003e   \u003c/div\u003e   \u003cdiv class\u003d\"btn\" style\u003d\"    background-color: inherit;    padding-right: 30px;    padding-top: 0px;    padding-bottom: 10px;    padding-left: 30px;    \"\u003e \u003cspan onclick\u003d\"next(this)\" type\u003d\"button\"\u003e\u003ci class\u003d\"fa fa-forward\" style\u003d\"    color: black;\"\u003e\u003c/i\u003e\u003c/span\u003e   \u003c/div\u003e  \u003c/div\u003e  \u003cbr\u003e ","value":{"A":"春天","B":"夏天","C":"秋天","D":"冬天"}},{"number":"17","header":"17.人类从蛤蜊身上能悟出什么道理？\u003caudio controls\u003d\"\" controlsList\u003d\"nodownload\"\u003e \r\n  \u003csource src\u003d\"http://localhost:8081/audios/BT/6/19 - Giáo trình chuẩn HSK 6 - SBT - question 16.mp3\" type\u003d\"audio/mpeg\"\u003e Your browser does not support the audio element. \r\n \u003c/audio\u003e \u003cdiv class\u003d\"btn-slide\"\u003e   \u003cdiv class\u003d\"btn\" style\u003d\"    background-color: inherit;    padding-top: 0px;    \"\u003e \u003cspan onclick\u003d\"previous(this)\" type\u003d\"button\"\u003e\u003ci class\u003d\"fa fa-backward\" style\u003d\"    color: black;\"\u003e\u003c/i\u003e\u003c/span\u003e   \u003c/div\u003e   \u003cdiv class\u003d\"btn\" style\u003d\"    background-color: inherit;    padding-right: 30px;    padding-top: 0px;    padding-bottom: 10px;    padding-left: 30px;    \"\u003e \u003cspan onclick\u003d\"next(this)\" type\u003d\"button\"\u003e\u003ci class\u003d\"fa fa-forward\" style\u003d\"    color: black;\"\u003e\u003c/i\u003e\u003c/span\u003e   \u003c/div\u003e  \u003c/div\u003e  \u003cbr\u003e ","value":{"A":"一生都要追求优雅","B":"父母必须对孩子负责","C":"父母抚养孩子不容易","D":"简约的生活是最健康的"}}],"category":"NGHE"},{"type":"3","number":"18","header":"\u003cdiv class\u003d\"qustion\"\u003e\u003cdiv class\u003d\"field-number\"\u003e  1 \u003c/div\u003e \u003cdiv class\u003d\"field-image\"\u003e  \u003cimg src\u003d\"!image_source!\" alt\u003d\"\"\u003e \u003c/div\u003e \u003cdiv class\u003d\"field-audio\"\u003e   \u003c/div\u003e \u003cdiv class\u003d\"text-center field-subject ans-hide\"\u003e  \u003cp class\u003d\"pinyin\"\u003e\u003c/p\u003e \u003c/div\u003e\u003c/div\u003e","body":[{"number":"18","value":{"A":"钟大夫的卫生室是镇里最正规的之一。","B":"在我的记忆里，几乎每一个冬天的晚上，奶奶都在灯下学习。","C":"一个华丽的转身，她在近乎疯狂的掌声中完美地结束了花样滑冰表演。","D":"河水在阳光的照耀下闪闪发光，但河比以前窄了很多，浪也没有以前大。"}}],"category":"DOC_HIEU"},{"type":"3","number":"19","header":"\u003cdiv class\u003d\"qustion\"\u003e\u003cdiv class\u003d\"field-number\"\u003e  1 \u003c/div\u003e \u003cdiv class\u003d\"field-image\"\u003e  \u003cimg src\u003d\"!image_source!\" alt\u003d\"\"\u003e \u003c/div\u003e \u003cdiv class\u003d\"field-audio\"\u003e   \u003c/div\u003e \u003cdiv class\u003d\"text-center field-subject ans-hide\"\u003e  \u003cp class\u003d\"pinyin\"\u003e\u003c/p\u003e \u003c/div\u003e\u003c/div\u003e","body":[{"number":"19","value":{"A":"他被《时代》杂志将其列入“20世纪最有影响的100个人”。","B":"没有翻不过的高山，没有走不出的沙漠，更没有超越不了的自我。","C":"蔚蓝的天空堆满造型奇异的云朵，有的像人，有的像动物，还有的像花。","D":"含杏仁油的护理液更容易渗透到受损的发丝中，从内部对发丝进行修补。"}}],"category":"DOC_HIEU"},{"type":"3","number":"20","header":"\u003cdiv class\u003d\"qustion\"\u003e\u003cdiv class\u003d\"field-number\"\u003e  1 \u003c/div\u003e \u003cdiv class\u003d\"field-image\"\u003e  \u003cimg src\u003d\"!image_source!\" alt\u003d\"\"\u003e \u003c/div\u003e \u003cdiv class\u003d\"field-audio\"\u003e   \u003c/div\u003e \u003cdiv class\u003d\"text-center field-subject ans-hide\"\u003e  \u003cp class\u003d\"pinyin\"\u003e\u003c/p\u003e \u003c/div\u003e\u003c/div\u003e","body":[{"number":"20","value":{"A":"空气不仅有体积，而且它还有重量。","B":"写论文不仅要驳错误的观点，而且会借助先人的看法。","C":"尽可能少犯错误，这是人的准则；不犯错误，那是天使的梦想。","D":"大雪过后，空气仿佛被过滤得干干净净，一切都变得那么纯洁而美好。"}}],"category":"DOC_HIEU"},{"type":"3","number":"21","header":"\u003cdiv class\u003d\"qustion\"\u003e\u003cdiv class\u003d\"field-number\"\u003e  1 \u003c/div\u003e \u003cdiv class\u003d\"field-image\"\u003e  \u003cimg src\u003d\"!image_source!\" alt\u003d\"\"\u003e \u003c/div\u003e \u003cdiv class\u003d\"field-audio\"\u003e   \u003c/div\u003e \u003cdiv class\u003d\"text-center field-subject ans-hide\"\u003e  \u003cp class\u003d\"pinyin\"\u003e板块-地体学说______了地壳运动现象，证明地球是一个生机勃勃的星体，它有着非常______的“新陈代谢”过程，有着______的过去和灿烂的未来。\u003c/p\u003e \u003c/div\u003e\u003c/div\u003e","body":[{"number":"21","value":{"A":"解释     活跃     辉煌","B":"发现     活泼     惊人","C":"发明     复杂     广阔","D":"展现     古怪     光荣"}}],"category":"DOC_HIEU"},{"type":"3","number":"22","header":"\u003cdiv class\u003d\"qustion\"\u003e\u003cdiv class\u003d\"field-number\"\u003e  1 \u003c/div\u003e \u003cdiv class\u003d\"field-image\"\u003e  \u003cimg src\u003d\"!image_source!\" alt\u003d\"\"\u003e \u003c/div\u003e \u003cdiv class\u003d\"field-audio\"\u003e   \u003c/div\u003e \u003cdiv class\u003d\"text-center field-subject ans-hide\"\u003e  \u003cp class\u003d\"pinyin\"\u003e______的采访时间已过大半，桌上的那杯茶未动。我______着周先生。他全神贯注，谈话仍旧有条不紊地进行着，没有______，没有停顿，谁也无法______这位科学家严谨的思维。\u003c/p\u003e \u003c/div\u003e\u003c/div\u003e","body":[{"number":"22","value":{"A":"打算     注意     迷惑     停止","B":"计划     凝视     混乱     断绝","C":"预测     审视     顾虑     拒绝","D":"预定     注视     跳跃     打断"}}],"category":"DOC_HIEU"},{"type":"3","number":"23","header":"\u003cdiv class\u003d\"qustion\"\u003e\u003cdiv class\u003d\"field-number\"\u003e  1 \u003c/div\u003e \u003cdiv class\u003d\"field-image\"\u003e  \u003cimg src\u003d\"!image_source!\" alt\u003d\"\"\u003e \u003c/div\u003e \u003cdiv class\u003d\"field-audio\"\u003e   \u003c/div\u003e \u003cdiv class\u003d\"text-center field-subject ans-hide\"\u003e  \u003cp class\u003d\"pinyin\"\u003e______不要因为矿物质在人体内含量极小就______它的价值，须知它们对维持人体中的一些决定性的新陈代谢是十分必要的。______缺少了这些必需的微量元素，人体就会出现疾病，______危及生命。\u003c/p\u003e \u003c/div\u003e\u003c/div\u003e","body":[{"number":"23","value":{"A":"总之     小看     与其     以至","B":"据悉     轻视     果然     乃至","C":"千万     忽视     一旦     甚至","D":"偏偏     漠视     随着     随后"}}],"category":"DOC_HIEU"},{"type":"6","number":"24-28","header":"苍蝇是声名狼藉的“逐臭之夫”，凡是脏臭污秽的地方，都有它们的踪迹。\n苍蝇的嗅觉特别灵敏，（24）\u003cspan class\u003d\"child-number\" data-child\u003d\"31604\" id\u003d\"24\" onclick\u003d\"chooseQuestion(24)\" style\u003d\"cursor: pointer;border-bottom: 1px solid #39a0ff;color:red\" selected\u003d\"false\"\u003e___\u003cspan class\u003d\"child-select rev-hide\"\u003e\u003c/span\u003e\u003c/span\u003e。但是苍蝇并没有“鼻子”，它靠什么来闻呢?原来苍蝇的嗅觉感受器分布在头部的一对触角上，每个触角有一个“鼻孔”与外界相通，内含上百个嗅觉神经细胞。（25）\u003cspan class\u003d\"child-number\" data-child\u003d\"31604\" id\u003d\"25\" onclick\u003d\"chooseQuestion(25)\" style\u003d\"cursor: pointer;border-bottom: 1px solid #39a0ff;color:red\" selected\u003d\"false\"\u003e___\u003cspan class\u003d\"child-select rev-hide\"\u003e\u003c/span\u003e\u003c/span\u003e，这些神经会立即把气味刺激转变成神经电脉冲，送往大脑，大脑根据不同气味物质所产生的神经电脉冲的不同，就可区别出不同气味的物质。因此，苍蝇的触角像是一台灵敏的气体分析仪。\n仿生学家由此得到启发，（26）\u003cspan class\u003d\"child-number\" data-child\u003d\"31604\" id\u003d\"26\" onclick\u003d\"chooseQuestion(26)\" style\u003d\"cursor: pointer;border-bottom: 1px solid #39a0ff;color:red\" selected\u003d\"false\"\u003e___\u003cspan class\u003d\"child-select rev-hide\"\u003e\u003c/span\u003e\u003c/span\u003e，仿制出一种十分奇特的小型气体分析仪。这种仪器的“探头”不是金属，（27）\u003cspan class\u003d\"child-number\" data-child\u003d\"31604\" id\u003d\"27\" onclick\u003d\"chooseQuestion(27)\" style\u003d\"cursor: pointer;border-bottom: 1px solid #39a0ff;color:red\" selected\u003d\"false\"\u003e___\u003cspan class\u003d\"child-select rev-hide\"\u003e\u003c/span\u003e\u003c/span\u003e。就是把非常纤细的微电极插到苍蝇的嗅觉神经上，将引导出来的神经电信号经电子线路放大后，传送给分析器；分析器一经发现气味物质的信号，便能发出警报。这种仪器已经被安装在宇宙飞船的座舱里，（28）\u003cspan class\u003d\"child-number\" data-child\u003d\"31604\" id\u003d\"28\" onclick\u003d\"chooseQuestion(28)\" style\u003d\"cursor: pointer;border-bottom: 1px solid #39a0ff;color:red\" selected\u003d\"false\"\u003e___\u003cspan class\u003d\"child-select rev-hide\"\u003e\u003c/span\u003e\u003c/span\u003e。这种小型气体分析仪，也可测量潜水艇和矿井里的有害气体。","body":[{"number":"24-28","value":{"A":"根据苍蝇嗅觉器官的结构和功能","B":"远在几千米外的气味也能嗅到","C":"用来检测舱内气体的成分","D":"而是活的苍蝇","E":"若有气味进入“鼻孔”"}}],"category":"DOC_HIEU"},{"type":"2","number":"29-32","header":"活化石指先发现化石再发现活体，或活体与确认的化石属同一种且同时存在。于是就有了一些延续了上千万年的古老生物，与其同时代的其他生物早已绝灭，只有它们独自保留下来，适应了现代的环境，生活在一个极其狭小的区域，被称为“活化石”。\n1938年在非洲东南部海中发现的矛尾鱼，是世界闻名的一种活化石。中国的银杏树、水杉，哺乳动物大熊猫、中华鲟，均被世界公认为珍贵的活化石。\n银杏树又名白果树，古又称鸭脚树或公孙树。远在二亿七千多万年前，银杏的祖先就开始出现了。到了一亿七千多万年前，银杏已和当时称霸世界的恐龙一样遍布世界各地，后来，绝大部分银杏像恐龙一样灭绝了，只在中国部分地区保存下来一点点，流传至今，成为稀世之宝。浙江天目山一带尚可见到野生银杏。故银杏有“活化石”、“植物中的熊猫”之称。\n水杉树姿优美，枝叶繁茂，叶色多变而独具一格。它曾广泛分布于北半球。但经过第四纪冰期以后，它们几乎全部绝灭。20世纪40年代，科学家在中国的四川、湖北和湖南均发现水杉尚有留存，其后，这个曾被认为早已在世界上绝迹的树种迅速传播于世。水杉不仅是珍贵的“活化石”，而且它有很强的生命力和广泛的适应性，它生长迅速，是优良的绿化树种，现在不但在中国各地广泛栽培，世界很多国家也争相引种，使这珍贵的树木得以在全球范围内生生不息。","body":[{"number":"29","header":"关于“活化石”，下列哪项正确?","value":{"A":"先发现化石再发现活体","B":"对生存空间没有特殊要求","C":"化石与活体同时被发现","D":"是活了上千万年的动植物"}},{"number":"30","header":"银杏树古代又称为：","value":{"A":"化石树","B":"鸭脚树","C":"公子树","D":"熊猫树"}},{"number":"31","header":"银杏树的繁盛时期在：","value":{"A":"一千多万年前","B":"恐龙灭绝的时候","C":"二亿七千多万年前","D":"一亿七千多万年前"}},{"number":"32","header":"水杉的特点是：","value":{"A":"适应环境的能力很强","B":"在世界各地均有发现","C":"生长速度慢于其他树","D":"仅可栽种于中国南方"}}],"category":"DOC_HIEU"},{"type":"2","number":"33-36","header":"5年前，一位老人在海边发现了一只浑身覆盖着石油、饿得奄奄一息的企鹅。老人把企鹅带回了家，给它取名Dindim。\nDindim是一只麦哲伦企鹅。之所以叫麦哲伦企鹅，是因为著名航海家麦哲伦于1519年最早发现了它们，后来科学界就以麦哲伦命名该物种了。这种企鹅主要分布于南美洲南端海域的群岛中，是温带地区企鹅类中极具代表性的物种。\n老人给Dindim清理黏附在羽毛上的油渍，使它身上不再有难闻的气味；喂鱼给它吃，让它尽快强壮起来。有了老人的悉心照料，Dindim很快得以康复。老人把它带到海边，想让它回家，Dindim却没有走，它在老人身边整整待了11个月，直到它开始换毛才离开。\n老人本以为这辈子不会再见到Dindim了，令他诧异的是，几个月后，Dindim又回来了，而且大模大样地跟着老人回了家。更为奇妙的是，此后，每年的6月，Dindim都会如期出现，次年的2月再回到阿根廷和智利的海岸。而它每年来看望老人要游行的距离超过3000公里。\n老人说，Dindim与他越来越亲密，每年他们一相见，Dindim就会愉快地摇晃尾巴，发出欢快的叫声，老人也像爱自己的孩子一样爱着Dindim。他相信Dindim也爱他，因为Dindim喜欢待在老人的腿上等着老人给它喂食，还允许老人把它抱起来，除了老人之外，任何人想接近Dindim，都会被啄。\nDindim为什么会和老人这么亲近，还要每年不远万里来和老人团聚，有生物学家认为，可能是企鹅把老人当成了家人，也可能是Dindim认为老人也是一只企鹅。至于真相，只有企鹅能够告诉你。","body":[{"number":"33","header":"5年前，老人发现企鹅时，那只企鹅：","value":{"A":"饿得没有了呼吸","B":"身上沾满了石油","C":"身上已开始换毛","D":"非常想有一个家"}},{"number":"34","header":"关于“麦哲伦企鹅”名字的来源，下列哪项正确?","value":{"A":"救了Dindim的老人给起的","B":"发现这一物种的人给起的","C":"以企鹅栖息地的地名而命名","D":"以最早发现人的名字而命名"}},{"number":"35","header":"老人认为最奇妙的事情是：","value":{"A":"Dindim康复之后一直没有离开他","B":"Dindim大大方方跟着老人回了家","C":"每年6月，Dindim都会准时来看他","D":"Dindim居然能够游3000公里的距离"}},{"number":"36","header":"关于企鹅为什么会和老人这","value":{"A":"老人行事风格很想企鹅","B":"老人把企鹅当成了我了","C":"这个答案只有企鹅知道","D":"别人的亲近让企鹅不愉快"}}],"category":"DOC_HIEU"}]