[{"type":"1","number":"1","header":"\u003cdiv class\u003d\"qustion\"\u003e\u003cdiv class\u003d\"field-number\"\u003e  1 \u003c/div\u003e \u003cdiv class\u003d\"field-image\"\u003e  \u003cimg src\u003d\"http://localhost:8081/images/BT/1/1.11.1.jpg\" alt\u003d\"\"\u003e \u003c/div\u003e \u003cdiv class\u003d\"field-audio\"\u003e  \u003caudio controls\u003d\"\" controlsList\u003d\"nodownload\"\u003e \r\n  \u003csource src\u003d\"http://localhost:8081/audios/BT/1/11-1 - Giáo trình chuẩn HSK 1 - Sách bài tập - question 1.mp3\" type\u003d\"audio/mpeg\"\u003e Your browser does not support the audio element. \r\n \u003c/audio\u003e \u003cdiv class\u003d\"btn-slide\"\u003e   \u003cdiv class\u003d\"btn\" style\u003d\"    background-color: inherit;    padding-top: 0px;    \"\u003e \u003cspan onclick\u003d\"previous(this)\" type\u003d\"button\"\u003e\u003ci class\u003d\"fa fa-backward\" style\u003d\"    color: black;\"\u003e\u003c/i\u003e\u003c/span\u003e   \u003c/div\u003e   \u003cdiv class\u003d\"btn\" style\u003d\"    background-color: inherit;    padding-right: 30px;    padding-top: 0px;    padding-bottom: 10px;    padding-left: 30px;    \"\u003e \u003cspan onclick\u003d\"next(this)\" type\u003d\"button\"\u003e\u003ci class\u003d\"fa fa-forward\" style\u003d\"    color: black;\"\u003e\u003c/i\u003e\u003c/span\u003e   \u003c/div\u003e  \u003c/div\u003e  \u003cbr\u003e  \u003c/div\u003e \u003cdiv class\u003d\"text-center field-subject ans-hide\"\u003e  \u003cp class\u003d\"pinyin\"\u003e吃饭\u003c/p\u003e \u003c/div\u003e\u003c/div\u003e","body":[{"number":"1","value":{"A":"","B":""}}],"category":"NGHE"},{"type":"1","number":"2","header":"\u003cdiv class\u003d\"qustion\"\u003e\u003cdiv class\u003d\"field-number\"\u003e  1 \u003c/div\u003e \u003cdiv class\u003d\"field-image\"\u003e  \u003cimg src\u003d\"http://localhost:8081/images/BT/1/1.11.2.jpg\" alt\u003d\"\"\u003e \u003c/div\u003e \u003cdiv class\u003d\"field-audio\"\u003e  \u003caudio controls\u003d\"\" controlsList\u003d\"nodownload\"\u003e \r\n  \u003csource src\u003d\"http://localhost:8081/audios/BT/1/11-1 - Giáo trình chuẩn HSK 1 - Sách bài tập - question 2.mp3\" type\u003d\"audio/mpeg\"\u003e Your browser does not support the audio element. \r\n \u003c/audio\u003e \u003cdiv class\u003d\"btn-slide\"\u003e   \u003cdiv class\u003d\"btn\" style\u003d\"    background-color: inherit;    padding-top: 0px;    \"\u003e \u003cspan onclick\u003d\"previous(this)\" type\u003d\"button\"\u003e\u003ci class\u003d\"fa fa-backward\" style\u003d\"    color: black;\"\u003e\u003c/i\u003e\u003c/span\u003e   \u003c/div\u003e   \u003cdiv class\u003d\"btn\" style\u003d\"    background-color: inherit;    padding-right: 30px;    padding-top: 0px;    padding-bottom: 10px;    padding-left: 30px;    \"\u003e \u003cspan onclick\u003d\"next(this)\" type\u003d\"button\"\u003e\u003ci class\u003d\"fa fa-forward\" style\u003d\"    color: black;\"\u003e\u003c/i\u003e\u003c/span\u003e   \u003c/div\u003e  \u003c/div\u003e  \u003cbr\u003e  \u003c/div\u003e \u003cdiv class\u003d\"text-center field-subject ans-hide\"\u003e  \u003cp class\u003d\"pinyin\"\u003e看电影\u003c/p\u003e \u003c/div\u003e\u003c/div\u003e","body":[{"number":"2","value":{"A":"","B":""}}],"category":"NGHE"},{"type":"1","number":"3","header":"\u003cdiv class\u003d\"qustion\"\u003e\u003cdiv class\u003d\"field-number\"\u003e  1 \u003c/div\u003e \u003cdiv class\u003d\"field-image\"\u003e  \u003cimg src\u003d\"http://localhost:8081/images/BT/1/1.11.3.jpg\" alt\u003d\"\"\u003e \u003c/div\u003e \u003cdiv class\u003d\"field-audio\"\u003e  \u003caudio controls\u003d\"\" controlsList\u003d\"nodownload\"\u003e \r\n  \u003csource src\u003d\"http://localhost:8081/audios/BT/1/11-1 - Giáo trình chuẩn HSK 1 - Sách bài tập - question 3.mp3\" type\u003d\"audio/mpeg\"\u003e Your browser does not support the audio element. \r\n \u003c/audio\u003e \u003cdiv class\u003d\"btn-slide\"\u003e   \u003cdiv class\u003d\"btn\" style\u003d\"    background-color: inherit;    padding-top: 0px;    \"\u003e \u003cspan onclick\u003d\"previous(this)\" type\u003d\"button\"\u003e\u003ci class\u003d\"fa fa-backward\" style\u003d\"    color: black;\"\u003e\u003c/i\u003e\u003c/span\u003e   \u003c/div\u003e   \u003cdiv class\u003d\"btn\" style\u003d\"    background-color: inherit;    padding-right: 30px;    padding-top: 0px;    padding-bottom: 10px;    padding-left: 30px;    \"\u003e \u003cspan onclick\u003d\"next(this)\" type\u003d\"button\"\u003e\u003ci class\u003d\"fa fa-forward\" style\u003d\"    color: black;\"\u003e\u003c/i\u003e\u003c/span\u003e   \u003c/div\u003e  \u003c/div\u003e  \u003cbr\u003e  \u003c/div\u003e \u003cdiv class\u003d\"text-center field-subject ans-hide\"\u003e  \u003cp class\u003d\"pinyin\"\u003e九点\u003c/p\u003e \u003c/div\u003e\u003c/div\u003e","body":[{"number":"3","value":{"A":"","B":""}}],"category":"NGHE"},{"type":"1","number":"4","header":"\u003cdiv class\u003d\"qustion\"\u003e\u003cdiv class\u003d\"field-number\"\u003e  1 \u003c/div\u003e \u003cdiv class\u003d\"field-image\"\u003e  \u003cimg src\u003d\"http://localhost:8081/images/BT/1/1.11.4.jpg\" alt\u003d\"\"\u003e \u003c/div\u003e \u003cdiv class\u003d\"field-audio\"\u003e  \u003caudio controls\u003d\"\" controlsList\u003d\"nodownload\"\u003e \r\n  \u003csource src\u003d\"http://localhost:8081/audios/BT/1/11-1 - Giáo trình chuẩn HSK 1 - Sách bài tập - question 4.mp3\" type\u003d\"audio/mpeg\"\u003e Your browser does not support the audio element. \r\n \u003c/audio\u003e \u003cdiv class\u003d\"btn-slide\"\u003e   \u003cdiv class\u003d\"btn\" style\u003d\"    background-color: inherit;    padding-top: 0px;    \"\u003e \u003cspan onclick\u003d\"previous(this)\" type\u003d\"button\"\u003e\u003ci class\u003d\"fa fa-backward\" style\u003d\"    color: black;\"\u003e\u003c/i\u003e\u003c/span\u003e   \u003c/div\u003e   \u003cdiv class\u003d\"btn\" style\u003d\"    background-color: inherit;    padding-right: 30px;    padding-top: 0px;    padding-bottom: 10px;    padding-left: 30px;    \"\u003e \u003cspan onclick\u003d\"next(this)\" type\u003d\"button\"\u003e\u003ci class\u003d\"fa fa-forward\" style\u003d\"    color: black;\"\u003e\u003c/i\u003e\u003c/span\u003e   \u003c/div\u003e  \u003c/div\u003e  \u003cbr\u003e  \u003c/div\u003e \u003cdiv class\u003d\"text-center field-subject ans-hide\"\u003e  \u003cp class\u003d\"pinyin\"\u003e看书\u003c/p\u003e \u003c/div\u003e\u003c/div\u003e","body":[{"number":"4","value":{"A":"","B":""}}],"category":"NGHE"},{"type":"1","number":"5","header":"\u003cdiv class\u003d\"qustion\"\u003e\u003cdiv class\u003d\"field-number\"\u003e  1 \u003c/div\u003e \u003cdiv class\u003d\"field-image\"\u003e  \u003cimg src\u003d\"http://localhost:8081/images/BT/1/1.11.5.jpg\" alt\u003d\"\"\u003e \u003c/div\u003e \u003cdiv class\u003d\"field-audio\"\u003e  \u003caudio controls\u003d\"\" controlsList\u003d\"nodownload\"\u003e \r\n  \u003csource src\u003d\"http://localhost:8081/audios/BT/1/11-1 - Giáo trình chuẩn HSK 1 - Sách bài tập - question 5.mp3\" type\u003d\"audio/mpeg\"\u003e Your browser does not support the audio element. \r\n \u003c/audio\u003e \u003cdiv class\u003d\"btn-slide\"\u003e   \u003cdiv class\u003d\"btn\" style\u003d\"    background-color: inherit;    padding-top: 0px;    \"\u003e \u003cspan onclick\u003d\"previous(this)\" type\u003d\"button\"\u003e\u003ci class\u003d\"fa fa-backward\" style\u003d\"    color: black;\"\u003e\u003c/i\u003e\u003c/span\u003e   \u003c/div\u003e   \u003cdiv class\u003d\"btn\" style\u003d\"    background-color: inherit;    padding-right: 30px;    padding-top: 0px;    padding-bottom: 10px;    padding-left: 30px;    \"\u003e \u003cspan onclick\u003d\"next(this)\" type\u003d\"button\"\u003e\u003ci class\u003d\"fa fa-forward\" style\u003d\"    color: black;\"\u003e\u003c/i\u003e\u003c/span\u003e   \u003c/div\u003e  \u003c/div\u003e  \u003cbr\u003e  \u003c/div\u003e \u003cdiv class\u003d\"text-center field-subject ans-hide\"\u003e  \u003cp class\u003d\"pinyin\"\u003e北京\u003c/p\u003e \u003c/div\u003e\u003c/div\u003e","body":[{"number":"5","value":{"A":"","B":""}}],"category":"NGHE"},{"type":"5","number":"6-10","header":"\u003cdiv class\u003d\"field-option\"\u003e \u003cspan class\u003d\"field-no\"\u003e\u003c/span\u003e\r\n\u003cp\u003e\u003cspan class\u003d\"label-words\" data-wid\u003d\"875\"\u003e\u003c/span\u003e\u003c/p\u003e\r\n\u003c/div\u003e\u003cdiv class\u003d\"field-option\"\u003e \u003cspan class\u003d\"field-no\"\u003e\u003c/span\u003e\r\n\u003cp\u003e\u003cspan class\u003d\"label-words\" data-wid\u003d\"875\"\u003e\u003c/span\u003e\u003c/p\u003e\r\n\u003c/div\u003e\u003cdiv class\u003d\"field-option\"\u003e \u003cspan class\u003d\"field-no\"\u003e\u003c/span\u003e\r\n\u003cp\u003e\u003cspan class\u003d\"label-words\" data-wid\u003d\"875\"\u003e\u003c/span\u003e\u003c/p\u003e\r\n\u003c/div\u003e\u003cdiv class\u003d\"field-option\"\u003e \u003cspan class\u003d\"field-no\"\u003e\u003c/span\u003e\r\n\u003cp\u003e\u003cspan class\u003d\"label-words\" data-wid\u003d\"875\"\u003e\u003c/span\u003e\u003c/p\u003e\r\n\u003c/div\u003e\u003cdiv class\u003d\"field-option\"\u003e \u003cspan class\u003d\"field-no\"\u003e\u003c/span\u003e\r\n\u003cp\u003e\u003cspan class\u003d\"label-words\" data-wid\u003d\"875\"\u003e\u003c/span\u003e\u003c/p\u003e\r\n\u003c/div\u003e","headingOptions":{"A":"\u003cdiv class\u003d\"field-image\"\u003e  \u003cimg src\u003d\"http://localhost:8081/images/BT/1/1.11.6.jpg\" alt\u003d\"\"\u003e \u003c/div\u003e \u003caudio controls\u003d\"\" controlsList\u003d\"nodownload\"\u003e \r\n  \u003csource src\u003d\"http://localhost:8081/audios/BT/1/11-1 - Giáo trình chuẩn HSK 1 - Sách bài tập - question 7.mp3\" type\u003d\"audio/mpeg\"\u003e Your browser does not support the audio element. \r\n \u003c/audio\u003e \u003cdiv class\u003d\"btn-slide\"\u003e   \u003cdiv class\u003d\"btn\" style\u003d\"    background-color: inherit;    padding-top: 0px;    \"\u003e \u003cspan onclick\u003d\"previous(this)\" type\u003d\"button\"\u003e\u003ci class\u003d\"fa fa-backward\" style\u003d\"    color: black;\"\u003e\u003c/i\u003e\u003c/span\u003e   \u003c/div\u003e   \u003cdiv class\u003d\"btn\" style\u003d\"    background-color: inherit;    padding-right: 30px;    padding-top: 0px;    padding-bottom: 10px;    padding-left: 30px;    \"\u003e \u003cspan onclick\u003d\"next(this)\" type\u003d\"button\"\u003e\u003ci class\u003d\"fa fa-forward\" style\u003d\"    color: black;\"\u003e\u003c/i\u003e\u003c/span\u003e   \u003c/div\u003e  \u003c/div\u003e  \u003cbr\u003e ","B":"\u003cdiv class\u003d\"field-image\"\u003e  \u003cimg src\u003d\"http://localhost:8081/images/BT/1/1.11.7.jpg\" alt\u003d\"\"\u003e \u003c/div\u003e \u003caudio controls\u003d\"\" controlsList\u003d\"nodownload\"\u003e \r\n  \u003csource src\u003d\"http://localhost:8081/audios/BT/1/11-1 - Giáo trình chuẩn HSK 1 - Sách bài tập - question 8.mp3\" type\u003d\"audio/mpeg\"\u003e Your browser does not support the audio element. \r\n \u003c/audio\u003e \u003cdiv class\u003d\"btn-slide\"\u003e   \u003cdiv class\u003d\"btn\" style\u003d\"    background-color: inherit;    padding-top: 0px;    \"\u003e \u003cspan onclick\u003d\"previous(this)\" type\u003d\"button\"\u003e\u003ci class\u003d\"fa fa-backward\" style\u003d\"    color: black;\"\u003e\u003c/i\u003e\u003c/span\u003e   \u003c/div\u003e   \u003cdiv class\u003d\"btn\" style\u003d\"    background-color: inherit;    padding-right: 30px;    padding-top: 0px;    padding-bottom: 10px;    padding-left: 30px;    \"\u003e \u003cspan onclick\u003d\"next(this)\" type\u003d\"button\"\u003e\u003ci class\u003d\"fa fa-forward\" style\u003d\"    color: black;\"\u003e\u003c/i\u003e\u003c/span\u003e   \u003c/div\u003e  \u003c/div\u003e  \u003cbr\u003e ","C":"\u003cdiv class\u003d\"field-image\"\u003e  \u003cimg src\u003d\"http://localhost:8081/images/BT/1/1.11.8.jpg\" alt\u003d\"\"\u003e \u003c/div\u003e \u003caudio controls\u003d\"\" controlsList\u003d\"nodownload\"\u003e \r\n  \u003csource src\u003d\"http://localhost:8081/audios/BT/1/11-1 - Giáo trình chuẩn HSK 1 - Sách bài tập - question 9.mp3\" type\u003d\"audio/mpeg\"\u003e Your browser does not support the audio element. \r\n \u003c/audio\u003e \u003cdiv class\u003d\"btn-slide\"\u003e   \u003cdiv class\u003d\"btn\" style\u003d\"    background-color: inherit;    padding-top: 0px;    \"\u003e \u003cspan onclick\u003d\"previous(this)\" type\u003d\"button\"\u003e\u003ci class\u003d\"fa fa-backward\" style\u003d\"    color: black;\"\u003e\u003c/i\u003e\u003c/span\u003e   \u003c/div\u003e   \u003cdiv class\u003d\"btn\" style\u003d\"    background-color: inherit;    padding-right: 30px;    padding-top: 0px;    padding-bottom: 10px;    padding-left: 30px;    \"\u003e \u003cspan onclick\u003d\"next(this)\" type\u003d\"button\"\u003e\u003ci class\u003d\"fa fa-forward\" style\u003d\"    color: black;\"\u003e\u003c/i\u003e\u003c/span\u003e   \u003c/div\u003e  \u003c/div\u003e  \u003cbr\u003e ","D":"\u003cdiv class\u003d\"field-image\"\u003e  \u003cimg src\u003d\"http://localhost:8081/images/BT/1/1.11.9.jpg\" alt\u003d\"\"\u003e \u003c/div\u003e \u003caudio controls\u003d\"\" controlsList\u003d\"nodownload\"\u003e \r\n  \u003csource src\u003d\"http://localhost:8081/audios/BT/1/11-1 - Giáo trình chuẩn HSK 1 - Sách bài tập - question 10.mp3\" type\u003d\"audio/mpeg\"\u003e Your browser does not support the audio element. \r\n \u003c/audio\u003e \u003cdiv class\u003d\"btn-slide\"\u003e   \u003cdiv class\u003d\"btn\" style\u003d\"    background-color: inherit;    padding-top: 0px;    \"\u003e \u003cspan onclick\u003d\"previous(this)\" type\u003d\"button\"\u003e\u003ci class\u003d\"fa fa-backward\" style\u003d\"    color: black;\"\u003e\u003c/i\u003e\u003c/span\u003e   \u003c/div\u003e   \u003cdiv class\u003d\"btn\" style\u003d\"    background-color: inherit;    padding-right: 30px;    padding-top: 0px;    padding-bottom: 10px;    padding-left: 30px;    \"\u003e \u003cspan onclick\u003d\"next(this)\" type\u003d\"button\"\u003e\u003ci class\u003d\"fa fa-forward\" style\u003d\"    color: black;\"\u003e\u003c/i\u003e\u003c/span\u003e   \u003c/div\u003e  \u003c/div\u003e  \u003cbr\u003e ","E":"\u003cdiv class\u003d\"field-image\"\u003e  \u003cimg src\u003d\"http://localhost:8081/images/BT/1/1.11.10.jpg\" alt\u003d\"\"\u003e \u003c/div\u003e \u003caudio controls\u003d\"\" controlsList\u003d\"nodownload\"\u003e \r\n  \u003csource src\u003d\"http://localhost:8081/audios/BT/1/11-1 - Giáo trình chuẩn HSK 1 - Sách bài tập - question 11.mp3\" type\u003d\"audio/mpeg\"\u003e Your browser does not support the audio element. \r\n \u003c/audio\u003e \u003cdiv class\u003d\"btn-slide\"\u003e   \u003cdiv class\u003d\"btn\" style\u003d\"    background-color: inherit;    padding-top: 0px;    \"\u003e \u003cspan onclick\u003d\"previous(this)\" type\u003d\"button\"\u003e\u003ci class\u003d\"fa fa-backward\" style\u003d\"    color: black;\"\u003e\u003c/i\u003e\u003c/span\u003e   \u003c/div\u003e   \u003cdiv class\u003d\"btn\" style\u003d\"    background-color: inherit;    padding-right: 30px;    padding-top: 0px;    padding-bottom: 10px;    padding-left: 30px;    \"\u003e \u003cspan onclick\u003d\"next(this)\" type\u003d\"button\"\u003e\u003ci class\u003d\"fa fa-forward\" style\u003d\"    color: black;\"\u003e\u003c/i\u003e\u003c/span\u003e   \u003c/div\u003e  \u003c/div\u003e  \u003cbr\u003e "},"body":[{"number":"6","header":"\u003cdiv class\u003d\"field-subject\"\u003e\u003cp\u003e男：现在几点？\n女：现在五点。\u003c/p\u003e\u003c/div\u003e\u003cdiv class\u003d\"field-select\"\u003e\u003c/div\u003e","value":{}},{"number":"7","header":"\u003cdiv class\u003d\"field-subject\"\u003e\u003cp\u003e男：你什么时候见李老师？\n女：我下午一点十分去学校见李老师。\u003c/p\u003e\u003c/div\u003e\u003cdiv class\u003d\"field-select\"\u003e\u003c/div\u003e","value":{}},{"number":"8","header":"\u003cdiv class\u003d\"field-subject\"\u003e\u003cp\u003e男：我想看电影。\n女：好啊，下午我有时间，我们一起去\u003c/p\u003e\u003c/div\u003e\u003cdiv class\u003d\"field-select\"\u003e\u003c/div\u003e","value":{}},{"number":"9","header":"\u003cdiv class\u003d\"field-subject\"\u003e\u003cp\u003e女；你星期六工作吗？\n男：不工作。\u003c/p\u003e\u003c/div\u003e\u003cdiv class\u003d\"field-select\"\u003e\u003c/div\u003e","value":{}},{"number":"10","header":"\u003cdiv class\u003d\"field-subject\"\u003e\u003cp\u003e女；你什么时候去北京？\n男：9月17号去，住三天。\u003c/p\u003e\u003c/div\u003e\u003cdiv class\u003d\"field-select\"\u003e\u003c/div\u003e","value":{}}],"category":"NGHE"},{"type":"3","number":"11","header":"\u003cdiv class\u003d\"qustion\"\u003e\u003cdiv class\u003d\"field-number\"\u003e  1 \u003c/div\u003e \u003cdiv class\u003d\"field-image\"\u003e  \u003cimg src\u003d\"!image_source!\" alt\u003d\"\"\u003e \u003c/div\u003e \u003cdiv class\u003d\"field-audio\"\u003e  \u003caudio controls\u003d\"\" controlsList\u003d\"nodownload\"\u003e \r\n  \u003csource src\u003d\"http://localhost:8081/audios/BT/1/11-1 - Giáo trình chuẩn HSK 1 - Sách bài tập - question 13.mp3\" type\u003d\"audio/mpeg\"\u003e Your browser does not support the audio element. \r\n \u003c/audio\u003e \u003cdiv class\u003d\"btn-slide\"\u003e   \u003cdiv class\u003d\"btn\" style\u003d\"    background-color: inherit;    padding-top: 0px;    \"\u003e \u003cspan onclick\u003d\"previous(this)\" type\u003d\"button\"\u003e\u003ci class\u003d\"fa fa-backward\" style\u003d\"    color: black;\"\u003e\u003c/i\u003e\u003c/span\u003e   \u003c/div\u003e   \u003cdiv class\u003d\"btn\" style\u003d\"    background-color: inherit;    padding-right: 30px;    padding-top: 0px;    padding-bottom: 10px;    padding-left: 30px;    \"\u003e \u003cspan onclick\u003d\"next(this)\" type\u003d\"button\"\u003e\u003ci class\u003d\"fa fa-forward\" style\u003d\"    color: black;\"\u003e\u003c/i\u003e\u003c/span\u003e   \u003c/div\u003e  \u003c/div\u003e  \u003cbr\u003e  \u003c/div\u003e \u003cdiv class\u003d\"text-center field-subject ans-hide\"\u003e  \u003cp class\u003d\"pinyin\"\u003e女：你什么时侯去北京？\n男：9月17号去，住三天。\u003c/p\u003e \u003c/div\u003e\u003c/div\u003e","body":[{"number":"11","value":{"A":"九点","B":"十点","C":"十一点"}}],"category":"NGHE"},{"type":"3","number":"12","header":"\u003cdiv class\u003d\"qustion\"\u003e\u003cdiv class\u003d\"field-number\"\u003e  1 \u003c/div\u003e \u003cdiv class\u003d\"field-image\"\u003e  \u003cimg src\u003d\"!image_source!\" alt\u003d\"\"\u003e \u003c/div\u003e \u003cdiv class\u003d\"field-audio\"\u003e  \u003caudio controls\u003d\"\" controlsList\u003d\"nodownload\"\u003e \r\n  \u003csource src\u003d\"http://localhost:8081/audios/BT/1/11-1 - Giáo trình chuẩn HSK 1 - Sách bài tập - question 14.mp3\" type\u003d\"audio/mpeg\"\u003e Your browser does not support the audio element. \r\n \u003c/audio\u003e \u003cdiv class\u003d\"btn-slide\"\u003e   \u003cdiv class\u003d\"btn\" style\u003d\"    background-color: inherit;    padding-top: 0px;    \"\u003e \u003cspan onclick\u003d\"previous(this)\" type\u003d\"button\"\u003e\u003ci class\u003d\"fa fa-backward\" style\u003d\"    color: black;\"\u003e\u003c/i\u003e\u003c/span\u003e   \u003c/div\u003e   \u003cdiv class\u003d\"btn\" style\u003d\"    background-color: inherit;    padding-right: 30px;    padding-top: 0px;    padding-bottom: 10px;    padding-left: 30px;    \"\u003e \u003cspan onclick\u003d\"next(this)\" type\u003d\"button\"\u003e\u003ci class\u003d\"fa fa-forward\" style\u003d\"    color: black;\"\u003e\u003c/i\u003e\u003c/span\u003e   \u003c/div\u003e  \u003c/div\u003e  \u003cbr\u003e  \u003c/div\u003e \u003cdiv class\u003d\"text-center field-subject ans-hide\"\u003e  \u003cp class\u003d\"pinyin\"\u003e我十点去工作，现在在家。\n问：他|她几点工作？\u003c/p\u003e \u003c/div\u003e\u003c/div\u003e","body":[{"number":"12","value":{"A":"八点五十分","B":"九点十分","C":"九点三十分"}}],"category":"NGHE"},{"type":"3","number":"13","header":"\u003cdiv class\u003d\"qustion\"\u003e\u003cdiv class\u003d\"field-number\"\u003e  1 \u003c/div\u003e \u003cdiv class\u003d\"field-image\"\u003e  \u003cimg src\u003d\"!image_source!\" alt\u003d\"\"\u003e \u003c/div\u003e \u003cdiv class\u003d\"field-audio\"\u003e  \u003caudio controls\u003d\"\" controlsList\u003d\"nodownload\"\u003e \r\n  \u003csource src\u003d\"http://localhost:8081/audios/BT/1/11-1 - Giáo trình chuẩn HSK 1 - Sách bài tập - question 15.mp3\" type\u003d\"audio/mpeg\"\u003e Your browser does not support the audio element. \r\n \u003c/audio\u003e \u003cdiv class\u003d\"btn-slide\"\u003e   \u003cdiv class\u003d\"btn\" style\u003d\"    background-color: inherit;    padding-top: 0px;    \"\u003e \u003cspan onclick\u003d\"previous(this)\" type\u003d\"button\"\u003e\u003ci class\u003d\"fa fa-backward\" style\u003d\"    color: black;\"\u003e\u003c/i\u003e\u003c/span\u003e   \u003c/div\u003e   \u003cdiv class\u003d\"btn\" style\u003d\"    background-color: inherit;    padding-right: 30px;    padding-top: 0px;    padding-bottom: 10px;    padding-left: 30px;    \"\u003e \u003cspan onclick\u003d\"next(this)\" type\u003d\"button\"\u003e\u003ci class\u003d\"fa fa-forward\" style\u003d\"    color: black;\"\u003e\u003c/i\u003e\u003c/span\u003e   \u003c/div\u003e  \u003c/div\u003e  \u003cbr\u003e  \u003c/div\u003e \u003cdiv class\u003d\"text-center field-subject ans-hide\"\u003e  \u003cp class\u003d\"pinyin\"\u003e现在八点，我们九点前去看电影。\n问：他们几点去看电影？\u003c/p\u003e \u003c/div\u003e\u003c/div\u003e","body":[{"number":"13","value":{"A":"看电影","B":"看书","C":"吃饭"}}],"category":"NGHE"},{"type":"3","number":"14","header":"\u003cdiv class\u003d\"qustion\"\u003e\u003cdiv class\u003d\"field-number\"\u003e  1 \u003c/div\u003e \u003cdiv class\u003d\"field-image\"\u003e  \u003cimg src\u003d\"!image_source!\" alt\u003d\"\"\u003e \u003c/div\u003e \u003cdiv class\u003d\"field-audio\"\u003e  \u003caudio controls\u003d\"\" controlsList\u003d\"nodownload\"\u003e \r\n  \u003csource src\u003d\"http://localhost:8081/audios/BT/1/11-1 - Giáo trình chuẩn HSK 1 - Sách bài tập - question 16.mp3\" type\u003d\"audio/mpeg\"\u003e Your browser does not support the audio element. \r\n \u003c/audio\u003e \u003cdiv class\u003d\"btn-slide\"\u003e   \u003cdiv class\u003d\"btn\" style\u003d\"    background-color: inherit;    padding-top: 0px;    \"\u003e \u003cspan onclick\u003d\"previous(this)\" type\u003d\"button\"\u003e\u003ci class\u003d\"fa fa-backward\" style\u003d\"    color: black;\"\u003e\u003c/i\u003e\u003c/span\u003e   \u003c/div\u003e   \u003cdiv class\u003d\"btn\" style\u003d\"    background-color: inherit;    padding-right: 30px;    padding-top: 0px;    padding-bottom: 10px;    padding-left: 30px;    \"\u003e \u003cspan onclick\u003d\"next(this)\" type\u003d\"button\"\u003e\u003ci class\u003d\"fa fa-forward\" style\u003d\"    color: black;\"\u003e\u003c/i\u003e\u003c/span\u003e   \u003c/div\u003e  \u003c/div\u003e  \u003cbr\u003e  \u003c/div\u003e \u003cdiv class\u003d\"text-center field-subject ans-hide\"\u003e  \u003cp class\u003d\"pinyin\"\u003e我中午十二点看书。\n问：他\\她十二点做什么？\u003c/p\u003e \u003c/div\u003e\u003c/div\u003e","body":[{"number":"14","value":{"A":"十点","B":"十二点","C":"两点"}}],"category":"NGHE"},{"type":"3","number":"15","header":"\u003cdiv class\u003d\"qustion\"\u003e\u003cdiv class\u003d\"field-number\"\u003e  1 \u003c/div\u003e \u003cdiv class\u003d\"field-image\"\u003e  \u003cimg src\u003d\"!image_source!\" alt\u003d\"\"\u003e \u003c/div\u003e \u003cdiv class\u003d\"field-audio\"\u003e  \u003caudio controls\u003d\"\" controlsList\u003d\"nodownload\"\u003e \r\n  \u003csource src\u003d\"http://localhost:8081/audios/BT/1/11-1 - Giáo trình chuẩn HSK 1 - Sách bài tập - question 17.mp3\" type\u003d\"audio/mpeg\"\u003e Your browser does not support the audio element. \r\n \u003c/audio\u003e \u003cdiv class\u003d\"btn-slide\"\u003e   \u003cdiv class\u003d\"btn\" style\u003d\"    background-color: inherit;    padding-top: 0px;    \"\u003e \u003cspan onclick\u003d\"previous(this)\" type\u003d\"button\"\u003e\u003ci class\u003d\"fa fa-backward\" style\u003d\"    color: black;\"\u003e\u003c/i\u003e\u003c/span\u003e   \u003c/div\u003e   \u003cdiv class\u003d\"btn\" style\u003d\"    background-color: inherit;    padding-right: 30px;    padding-top: 0px;    padding-bottom: 10px;    padding-left: 30px;    \"\u003e \u003cspan onclick\u003d\"next(this)\" type\u003d\"button\"\u003e\u003ci class\u003d\"fa fa-forward\" style\u003d\"    color: black;\"\u003e\u003c/i\u003e\u003c/span\u003e   \u003c/div\u003e  \u003c/div\u003e  \u003cbr\u003e  \u003c/div\u003e \u003cdiv class\u003d\"text-center field-subject ans-hide\"\u003e  \u003cp class\u003d\"pinyin\"\u003e他在北京住三天，星期五回家。\n问：他什么时候回家？\u003c/p\u003e \u003c/div\u003e\u003c/div\u003e","body":[{"number":"15","value":{"A":"星期三","B":"星期五","C":"不回家"}}],"category":"NGHE"},{"type":"1","number":"16","header":"\u003cdiv class\u003d\"qustion\"\u003e\u003cdiv class\u003d\"field-number\"\u003e  1 \u003c/div\u003e \u003cdiv class\u003d\"field-image\"\u003e  \u003cimg src\u003d\"http://localhost:8081/images/BT/1/我们.jpg\" alt\u003d\"\"\u003e \u003c/div\u003e \u003cdiv class\u003d\"field-audio\"\u003e   \u003c/div\u003e \u003cdiv class\u003d\"text-center field-subject ans-hide\"\u003e  \u003cp class\u003d\"pinyin\"\u003e1.11.16\u003c/p\u003e \u003c/div\u003e\u003c/div\u003e","body":[{"number":"16","value":{"A":"","B":""}}],"category":"DOC_HIEU"},{"type":"1","number":"17","header":"\u003cdiv class\u003d\"qustion\"\u003e\u003cdiv class\u003d\"field-number\"\u003e  1 \u003c/div\u003e \u003cdiv class\u003d\"field-image\"\u003e  \u003cimg src\u003d\"http://localhost:8081/images/BT/1/米饭.jpg\" alt\u003d\"\"\u003e \u003c/div\u003e \u003cdiv class\u003d\"field-audio\"\u003e   \u003c/div\u003e \u003cdiv class\u003d\"text-center field-subject ans-hide\"\u003e  \u003cp class\u003d\"pinyin\"\u003e1.11.17\u003c/p\u003e \u003c/div\u003e\u003c/div\u003e","body":[{"number":"17","value":{"A":"","B":""}}],"category":"DOC_HIEU"},{"type":"1","number":"18","header":"\u003cdiv class\u003d\"qustion\"\u003e\u003cdiv class\u003d\"field-number\"\u003e  1 \u003c/div\u003e \u003cdiv class\u003d\"field-image\"\u003e  \u003cimg src\u003d\"http://localhost:8081/images/BT/1/中午.jpg\" alt\u003d\"\"\u003e \u003c/div\u003e \u003cdiv class\u003d\"field-audio\"\u003e   \u003c/div\u003e \u003cdiv class\u003d\"text-center field-subject ans-hide\"\u003e  \u003cp class\u003d\"pinyin\"\u003e1.11.18\u003c/p\u003e \u003c/div\u003e\u003c/div\u003e","body":[{"number":"18","value":{"A":"","B":""}}],"category":"DOC_HIEU"},{"type":"1","number":"19","header":"\u003cdiv class\u003d\"qustion\"\u003e\u003cdiv class\u003d\"field-number\"\u003e  1 \u003c/div\u003e \u003cdiv class\u003d\"field-image\"\u003e  \u003cimg src\u003d\"http://localhost:8081/images/BT/1/工作.jpg\" alt\u003d\"\"\u003e \u003c/div\u003e \u003cdiv class\u003d\"field-audio\"\u003e   \u003c/div\u003e \u003cdiv class\u003d\"text-center field-subject ans-hide\"\u003e  \u003cp class\u003d\"pinyin\"\u003e1.11.19\u003c/p\u003e \u003c/div\u003e\u003c/div\u003e","body":[{"number":"19","value":{"A":"","B":""}}],"category":"DOC_HIEU"},{"type":"1","number":"20","header":"\u003cdiv class\u003d\"qustion\"\u003e\u003cdiv class\u003d\"field-number\"\u003e  1 \u003c/div\u003e \u003cdiv class\u003d\"field-image\"\u003e  \u003cimg src\u003d\"http://localhost:8081/images/BT/1/电影.jpg\" alt\u003d\"\"\u003e \u003c/div\u003e \u003cdiv class\u003d\"field-audio\"\u003e   \u003c/div\u003e \u003cdiv class\u003d\"text-center field-subject ans-hide\"\u003e  \u003cp class\u003d\"pinyin\"\u003e1.11.20\u003c/p\u003e \u003c/div\u003e\u003c/div\u003e","body":[{"number":"20","value":{"A":"","B":""}}],"category":"DOC_HIEU"},{"type":"5","number":"21-25","header":"\u003cdiv class\u003d\"field-option\"\u003e \u003cspan class\u003d\"field-no\"\u003eB\u003c/span\u003e\r\n\u003cp\u003e\u003cspan class\u003d\"label-words\" data-wid\u003d\"875\"\u003e我不去，没有时间。\u003c/span\u003e\u003c/p\u003e\r\n\u003c/div\u003e\u003cdiv class\u003d\"field-option\"\u003e \u003cspan class\u003d\"field-no\"\u003eC\u003c/span\u003e\r\n\u003cp\u003e\u003cspan class\u003d\"label-words\" data-wid\u003d\"875\"\u003e不工作，你12点来吧。\u003c/span\u003e\u003c/p\u003e\r\n\u003c/div\u003e\u003cdiv class\u003d\"field-option\"\u003e \u003cspan class\u003d\"field-no\"\u003eD\u003c/span\u003e\r\n\u003cp\u003e\u003cspan class\u003d\"label-words\" data-wid\u003d\"875\"\u003e星期五前。\u003c/span\u003e\u003c/p\u003e\r\n\u003c/div\u003e\u003cdiv class\u003d\"field-option\"\u003e \u003cspan class\u003d\"field-no\"\u003eE\u003c/span\u003e\r\n\u003cp\u003e\u003cspan class\u003d\"label-words\" data-wid\u003d\"875\"\u003e她不想去。\u003c/span\u003e\u003c/p\u003e\r\n\u003c/div\u003e\u003cdiv class\u003d\"field-option\"\u003e \u003cspan class\u003d\"field-no\"\u003eF\u003c/span\u003e\r\n\u003cp\u003e\u003cspan class\u003d\"label-words\" data-wid\u003d\"875\"\u003e好的，谢谢！\u003c/span\u003e\u003c/p\u003e\r\n\u003c/div\u003e","headingOptions":{"B":"我不去，没有时间。","C":"不工作，你12点来吧。","D":"星期五前。","E":"她不想去。","F":"好的，谢谢！"},"body":[{"number":"21","header":"\u003cdiv class\u003d\"field-subject\"\u003e\u003cp\u003e下午三点你去学校吗？\u003c/p\u003e\u003c/div\u003e\u003cdiv class\u003d\"field-select\"\u003e\u003c/div\u003e","value":{}},{"number":"22","header":"\u003cdiv class\u003d\"field-subject\"\u003e\u003cp\u003e你什么时候回北京？\u003c/p\u003e\u003c/div\u003e\u003cdiv class\u003d\"field-select\"\u003e\u003c/div\u003e","value":{}},{"number":"23","header":"\u003cdiv class\u003d\"field-subject\"\u003e\u003cp\u003e中午你工作吗？\u003c/p\u003e\u003c/div\u003e\u003cdiv class\u003d\"field-select\"\u003e\u003c/div\u003e","value":{}},{"number":"24","header":"\u003cdiv class\u003d\"field-subject\"\u003e\u003cp\u003e你中午去吃饭吗？\u003c/p\u003e\u003c/div\u003e\u003cdiv class\u003d\"field-select\"\u003e\u003c/div\u003e","value":{}},{"number":"25","header":"\u003cdiv class\u003d\"field-subject\"\u003e\u003cp\u003e大卫去看电影吗？\u003c/p\u003e\u003c/div\u003e\u003cdiv class\u003d\"field-select\"\u003e\u003c/div\u003e","value":{}}],"category":"DOC_HIEU"},{"type":"5","number":"26-30","header":"\u003cdiv class\u003d\"field-option\"\u003e \u003cspan class\u003d\"field-no\"\u003eB\u003c/span\u003e\r\n\u003cp\u003e\u003cspan class\u003d\"label-words\" data-wid\u003d\"875\"\u003e分\u003c/span\u003e\u003c/p\u003e\r\n\u003c/div\u003e\u003cdiv class\u003d\"field-option\"\u003e \u003cspan class\u003d\"field-no\"\u003eC\u003c/span\u003e\r\n\u003cp\u003e\u003cspan class\u003d\"label-words\" data-wid\u003d\"875\"\u003e时候\u003c/span\u003e\u003c/p\u003e\r\n\u003c/div\u003e\u003cdiv class\u003d\"field-option\"\u003e \u003cspan class\u003d\"field-no\"\u003eD\u003c/span\u003e\r\n\u003cp\u003e\u003cspan class\u003d\"label-words\" data-wid\u003d\"875\"\u003e名字\u003c/span\u003e\u003c/p\u003e\r\n\u003c/div\u003e\u003cdiv class\u003d\"field-option\"\u003e \u003cspan class\u003d\"field-no\"\u003eE\u003c/span\u003e\r\n\u003cp\u003e\u003cspan class\u003d\"label-words\" data-wid\u003d\"875\"\u003e前\u003c/span\u003e\u003c/p\u003e\r\n\u003c/div\u003e\u003cdiv class\u003d\"field-option\"\u003e \u003cspan class\u003d\"field-no\"\u003eF\u003c/span\u003e\r\n\u003cp\u003e\u003cspan class\u003d\"label-words\" data-wid\u003d\"875\"\u003e住\u003c/span\u003e\u003c/p\u003e\r\n\u003c/div\u003e","headingOptions":{"B":"分","C":"时候","D":"名字","E":"前","F":"住"},"body":[{"number":"26","header":"\u003cdiv class\u003d\"field-subject\"\u003e\u003cp\u003e我在王方家（）一个星期，星期六回家。\u003c/p\u003e\u003c/div\u003e\u003cdiv class\u003d\"field-select\"\u003e\u003c/div\u003e","value":{}},{"number":"27","header":"\u003cdiv class\u003d\"field-subject\"\u003e\u003cp\u003e你什么（）有时间？我们去看电影。\u003c/p\u003e\u003c/div\u003e\u003cdiv class\u003d\"field-select\"\u003e\u003c/div\u003e","value":{}},{"number":"28","header":"\u003cdiv class\u003d\"field-subject\"\u003e\u003cp\u003e现在中午十二（），你去吃饭吗？\u003c/p\u003e\u003c/div\u003e\u003cdiv class\u003d\"field-select\"\u003e\u003c/div\u003e","value":{}},{"number":"29","header":"\u003cdiv class\u003d\"field-subject\"\u003e\u003cp\u003e我现在工作，十二点十（）去吃饭。\u003c/p\u003e\u003c/div\u003e\u003cdiv class\u003d\"field-select\"\u003e\u003c/div\u003e","value":{}},{"number":"30","header":"\u003cdiv class\u003d\"field-subject\"\u003e\u003cp\u003e我八点（）在家。\u003c/p\u003e\u003c/div\u003e\u003cdiv class\u003d\"field-select\"\u003e\u003c/div\u003e","value":{}}],"category":"DOC_HIEU"}]