[{"type":"3","number":"1","header":"\u003cdiv class\u003d\"qustion\"\u003e\u003cdiv class\u003d\"field-number\"\u003e  1 \u003c/div\u003e \u003cdiv class\u003d\"field-image\"\u003e  \u003cimg src\u003d\"!image_source!\" alt\u003d\"\"\u003e \u003c/div\u003e \u003cdiv class\u003d\"field-audio\"\u003e   \u003c/div\u003e \u003cdiv class\u003d\"text-center field-subject ans-hide\"\u003e  \u003cp class\u003d\"pinyin\"\u003e活儿总算忙完了，他累得都要崩溃了，满脑子都是客户和协议。虽然困得要死，可躺在床上颠来倒去睡不着，心烦意乱之中，突然听到儿子的房间传来了朗读英语的声音，轻柔、平静，不知不觉中，他竟入睡了。\u003c/p\u003e \u003c/div\u003e\u003c/div\u003e","body":[{"number":"1","value":{"A":"他每天都学习英语","B":"他白天工作特别多","C":"他每天很晚才睡觉","D":"他晚上一直没睡觉"}}],"category":"NGHE"},{"type":"3","number":"2","header":"\u003cdiv class\u003d\"qustion\"\u003e\u003cdiv class\u003d\"field-number\"\u003e  1 \u003c/div\u003e \u003cdiv class\u003d\"field-image\"\u003e  \u003cimg src\u003d\"!image_source!\" alt\u003d\"\"\u003e \u003c/div\u003e \u003cdiv class\u003d\"field-audio\"\u003e  \u003caudio controls\u003d\"\" controlsList\u003d\"nodownload\"\u003e \r\n  \u003csource src\u003d\"http://localhost:8081/audios/BT/6/05 - Giáo trình chuẩn HSK 6 - SBT - question 1.mp3\" type\u003d\"audio/mpeg\"\u003e Your browser does not support the audio element. \r\n \u003c/audio\u003e \u003cdiv class\u003d\"btn-slide\"\u003e   \u003cdiv class\u003d\"btn\" style\u003d\"    background-color: inherit;    padding-top: 0px;    \"\u003e \u003cspan onclick\u003d\"previous(this)\" type\u003d\"button\"\u003e\u003ci class\u003d\"fa fa-backward\" style\u003d\"    color: black;\"\u003e\u003c/i\u003e\u003c/span\u003e   \u003c/div\u003e   \u003cdiv class\u003d\"btn\" style\u003d\"    background-color: inherit;    padding-right: 30px;    padding-top: 0px;    padding-bottom: 10px;    padding-left: 30px;    \"\u003e \u003cspan onclick\u003d\"next(this)\" type\u003d\"button\"\u003e\u003ci class\u003d\"fa fa-forward\" style\u003d\"    color: black;\"\u003e\u003c/i\u003e\u003c/span\u003e   \u003c/div\u003e  \u003c/div\u003e  \u003cbr\u003e  \u003c/div\u003e \u003cdiv class\u003d\"text-center field-subject ans-hide\"\u003e  \u003cp class\u003d\"pinyin\"\u003e人的头发中有一种叫作黑色素的物质，黑色素越多头发的颜色越黑，黑色素少了，头发便会发黄或变白。人进入老年，身体的各种机能会逐渐衰退，色素也会越来越少，所以头发就会渐渐变白。\u003c/p\u003e \u003c/div\u003e\u003c/div\u003e","body":[{"number":"2","value":{"A":"头发是否变白和人的肤色有关","B":"头发变白说明人各种机能变好","C":"头发的颜色取决于黑色素的多少","D":"黑色素的多少决定着头发的多少"}}],"category":"NGHE"},{"type":"3","number":"3","header":"\u003cdiv class\u003d\"qustion\"\u003e\u003cdiv class\u003d\"field-number\"\u003e  1 \u003c/div\u003e \u003cdiv class\u003d\"field-image\"\u003e  \u003cimg src\u003d\"!image_source!\" alt\u003d\"\"\u003e \u003c/div\u003e \u003cdiv class\u003d\"field-audio\"\u003e  \u003caudio controls\u003d\"\" controlsList\u003d\"nodownload\"\u003e \r\n  \u003csource src\u003d\"http://localhost:8081/audios/BT/6/05 - Giáo trình chuẩn HSK 6 - SBT - question 2.mp3\" type\u003d\"audio/mpeg\"\u003e Your browser does not support the audio element. \r\n \u003c/audio\u003e \u003cdiv class\u003d\"btn-slide\"\u003e   \u003cdiv class\u003d\"btn\" style\u003d\"    background-color: inherit;    padding-top: 0px;    \"\u003e \u003cspan onclick\u003d\"previous(this)\" type\u003d\"button\"\u003e\u003ci class\u003d\"fa fa-backward\" style\u003d\"    color: black;\"\u003e\u003c/i\u003e\u003c/span\u003e   \u003c/div\u003e   \u003cdiv class\u003d\"btn\" style\u003d\"    background-color: inherit;    padding-right: 30px;    padding-top: 0px;    padding-bottom: 10px;    padding-left: 30px;    \"\u003e \u003cspan onclick\u003d\"next(this)\" type\u003d\"button\"\u003e\u003ci class\u003d\"fa fa-forward\" style\u003d\"    color: black;\"\u003e\u003c/i\u003e\u003c/span\u003e   \u003c/div\u003e  \u003c/div\u003e  \u003cbr\u003e  \u003c/div\u003e \u003cdiv class\u003d\"text-center field-subject ans-hide\"\u003e  \u003cp class\u003d\"pinyin\"\u003e1915 年中国将清明节定为植树节，1928 年将植树节改为 3 月 12 日，这一设定一直沿用至今。此外，一些省市还根据当地的气候规律，规定了其他的植树日、植树周、植树月。\u003c/p\u003e \u003c/div\u003e\u003c/div\u003e","body":[{"number":"3","value":{"A":"1915年中国有了清明节","B":"1928年中国首创植树节","C":"很多省市有自己的植树节","D":"植树节在每年的3月12号"}}],"category":"NGHE"},{"type":"3","number":"4","header":"\u003cdiv class\u003d\"qustion\"\u003e\u003cdiv class\u003d\"field-number\"\u003e  1 \u003c/div\u003e \u003cdiv class\u003d\"field-image\"\u003e  \u003cimg src\u003d\"!image_source!\" alt\u003d\"\"\u003e \u003c/div\u003e \u003cdiv class\u003d\"field-audio\"\u003e  \u003caudio controls\u003d\"\" controlsList\u003d\"nodownload\"\u003e \r\n  \u003csource src\u003d\"http://localhost:8081/audios/BT/6/05 - Giáo trình chuẩn HSK 6 - SBT - question 3.mp3\" type\u003d\"audio/mpeg\"\u003e Your browser does not support the audio element. \r\n \u003c/audio\u003e \u003cdiv class\u003d\"btn-slide\"\u003e   \u003cdiv class\u003d\"btn\" style\u003d\"    background-color: inherit;    padding-top: 0px;    \"\u003e \u003cspan onclick\u003d\"previous(this)\" type\u003d\"button\"\u003e\u003ci class\u003d\"fa fa-backward\" style\u003d\"    color: black;\"\u003e\u003c/i\u003e\u003c/span\u003e   \u003c/div\u003e   \u003cdiv class\u003d\"btn\" style\u003d\"    background-color: inherit;    padding-right: 30px;    padding-top: 0px;    padding-bottom: 10px;    padding-left: 30px;    \"\u003e \u003cspan onclick\u003d\"next(this)\" type\u003d\"button\"\u003e\u003ci class\u003d\"fa fa-forward\" style\u003d\"    color: black;\"\u003e\u003c/i\u003e\u003c/span\u003e   \u003c/div\u003e  \u003c/div\u003e  \u003cbr\u003e  \u003c/div\u003e \u003cdiv class\u003d\"text-center field-subject ans-hide\"\u003e  \u003cp class\u003d\"pinyin\"\u003e盛文强长期从事海洋民间故事的采集整理，并出版了多部海洋题材小说。作为传统的农业国家，中国文学中的农业元素太多了，所以盛文强的“海洋文学”出现在读者面前时，不免让人眼前一亮。\u003c/p\u003e \u003c/div\u003e\u003c/div\u003e","body":[{"number":"4","value":{"A":"盛文强从小生活在农村","B":"盛文强的作品取材海洋","C":"盛文强很会讲民间故事","D":"盛文强特别喜欢看小说"}}],"category":"NGHE"},{"type":"3","number":"5","header":"\u003cdiv class\u003d\"qustion\"\u003e\u003cdiv class\u003d\"field-number\"\u003e  1 \u003c/div\u003e \u003cdiv class\u003d\"field-image\"\u003e  \u003cimg src\u003d\"!image_source!\" alt\u003d\"\"\u003e \u003c/div\u003e \u003cdiv class\u003d\"field-audio\"\u003e  \u003caudio controls\u003d\"\" controlsList\u003d\"nodownload\"\u003e \r\n  \u003csource src\u003d\"http://localhost:8081/audios/BT/6/05 - Giáo trình chuẩn HSK 6 - SBT - question 4.mp3\" type\u003d\"audio/mpeg\"\u003e Your browser does not support the audio element. \r\n \u003c/audio\u003e \u003cdiv class\u003d\"btn-slide\"\u003e   \u003cdiv class\u003d\"btn\" style\u003d\"    background-color: inherit;    padding-top: 0px;    \"\u003e \u003cspan onclick\u003d\"previous(this)\" type\u003d\"button\"\u003e\u003ci class\u003d\"fa fa-backward\" style\u003d\"    color: black;\"\u003e\u003c/i\u003e\u003c/span\u003e   \u003c/div\u003e   \u003cdiv class\u003d\"btn\" style\u003d\"    background-color: inherit;    padding-right: 30px;    padding-top: 0px;    padding-bottom: 10px;    padding-left: 30px;    \"\u003e \u003cspan onclick\u003d\"next(this)\" type\u003d\"button\"\u003e\u003ci class\u003d\"fa fa-forward\" style\u003d\"    color: black;\"\u003e\u003c/i\u003e\u003c/span\u003e   \u003c/div\u003e  \u003c/div\u003e  \u003cbr\u003e  \u003c/div\u003e \u003cdiv class\u003d\"text-center field-subject ans-hide\"\u003e  \u003cp class\u003d\"pinyin\"\u003e我带着狗去郊游，狗发现了野兔就兴奋地前去追赶。野兔明明知道狗来了，却像没这事一样，照样坐在那儿吃草，直到狗跑近了，野兔才一跃而起，迅速跑开，当它跑到自认为安全的地方，便又马上安定下来。\u003c/p\u003e \u003c/div\u003e\u003c/div\u003e","body":[{"number":"5","value":{"A":"狗追近了，兔子才会躲开","B":"兔子看到狗就会拼命地跑","C":"兔子看到狗就会心神不定","D":"我专程去郊外看狗追兔子"}}],"category":"NGHE"},{"type":"2","number":"6-10","header":"女：今天来参加我们访谈节目的是年轻朋友非常崇拜的著名节目主持人刘可心。欢迎您！您知道年轻朋友私底下怎么称呼您吗？\n男：“可心同学”？\n女：对。\n男：可以这么叫我。我喜欢这个称呼。\n女：那好，咱们就这么叫了。可心同学，很多听众喜欢听您说话，认为您思维角度与众不同，听您说话不只是听听而已，关键是总能受到启发。\n男：过奖了。我之所以能成为今天的我，无非是和读书，特别是和读名著有关。阅读经典，肯定会对我们的人生产生影响。比如，我小时候对“美”和“丑”的理解，就跟读法国作家雨果的《巴黎圣母院》有关，这本书让我意识到，不能光凭外表长得不好看就觉得这个人也不好。\n女：名著这么好，有些孩子怎么就是不愿意读呢？\n男：主要是因为老师家长把这事当任务布置给孩子，孩子就会觉得很累，甚至反感。读书不能勉强，其实读名著是件很好玩儿的事情，名著都是经受住了历史考验的。所以，家长要让孩子带着好奇心去读，他就有了动力。\n女：您的孩子喜欢读书吗？这不是隐私吧？\n男：当然不是。我的孩子非常喜欢读书。\n女：他读的第一本书是什么，您还记得吗？\n男：他认真读的第一本书是武侠小说。\n女：哦？\n男：在读书方面，我给他非常大的自由。我觉得最重要的是让他在年少时喜欢读书，而不是读哪本书。\n女：听说您的孩子马上就要高考了，而且选择的是历史？\n男：对，应该说他的选择跟他的阅读经历有关，他读金庸的武侠小说着迷，读完一遍还想读第二遍，书里涉及一些他不懂的内容，就到处查书查资料，这样他的阅读面就会不断向外延伸。\n女：这么说，名著也不需要读全？您怎么看古人说过的“读万卷书行万里路”？\n男：在我看来，不管行万里路还是读万卷书，关键得看走不走心，到哪儿赶紧拍照，奔下一个景点，万里路固然是走了，可一点儿用都没有。即使你没读万卷书，但把 10 本书给读明白了，要比囫囵吞枣读 100 本书好得多。\n","body":[{"number":"6","header":"6. 关于刘可心，可以知道什么？\n","value":{"A":"他很受年轻人欢迎","B":"他还没工作，是个学生","C":"他的话没有太大的价值","D":"他总能从生活中受到启发"}},{"number":"7","header":"7. 刘可心怎么评价自己？\n\u003caudio controls\u003d\"\" controlsList\u003d\"nodownload\"\u003e \r\n  \u003csource src\u003d\"http://localhost:8081/audios/BT/6/05 - Giáo trình chuẩn HSK 6 - SBT - question 6.mp3\" type\u003d\"audio/mpeg\"\u003e Your browser does not support the audio element. \r\n \u003c/audio\u003e \u003cdiv class\u003d\"btn-slide\"\u003e   \u003cdiv class\u003d\"btn\" style\u003d\"    background-color: inherit;    padding-top: 0px;    \"\u003e \u003cspan onclick\u003d\"previous(this)\" type\u003d\"button\"\u003e\u003ci class\u003d\"fa fa-backward\" style\u003d\"    color: black;\"\u003e\u003c/i\u003e\u003c/span\u003e   \u003c/div\u003e   \u003cdiv class\u003d\"btn\" style\u003d\"    background-color: inherit;    padding-right: 30px;    padding-top: 0px;    padding-bottom: 10px;    padding-left: 30px;    \"\u003e \u003cspan onclick\u003d\"next(this)\" type\u003d\"button\"\u003e\u003ci class\u003d\"fa fa-forward\" style\u003d\"    color: black;\"\u003e\u003c/i\u003e\u003c/span\u003e   \u003c/div\u003e  \u003c/div\u003e  \u003cbr\u003e ","value":{"A":"他在哪儿都会受表扬","B":"他的成功和读书有关","C":"他一直喜欢法国小说","D":"人长相难看心眼儿才好"}},{"number":"8","header":"8. 刘可心认为有的孩子不愿意读名著的原因是什么？\n\u003caudio controls\u003d\"\" controlsList\u003d\"nodownload\"\u003e \r\n  \u003csource src\u003d\"http://localhost:8081/audios/BT/6/05 - Giáo trình chuẩn HSK 6 - SBT - question 7.mp3\" type\u003d\"audio/mpeg\"\u003e Your browser does not support the audio element. \r\n \u003c/audio\u003e \u003cdiv class\u003d\"btn-slide\"\u003e   \u003cdiv class\u003d\"btn\" style\u003d\"    background-color: inherit;    padding-top: 0px;    \"\u003e \u003cspan onclick\u003d\"previous(this)\" type\u003d\"button\"\u003e\u003ci class\u003d\"fa fa-backward\" style\u003d\"    color: black;\"\u003e\u003c/i\u003e\u003c/span\u003e   \u003c/div\u003e   \u003cdiv class\u003d\"btn\" style\u003d\"    background-color: inherit;    padding-right: 30px;    padding-top: 0px;    padding-bottom: 10px;    padding-left: 30px;    \"\u003e \u003cspan onclick\u003d\"next(this)\" type\u003d\"button\"\u003e\u003ci class\u003d\"fa fa-forward\" style\u003d\"    color: black;\"\u003e\u003c/i\u003e\u003c/span\u003e   \u003c/div\u003e  \u003c/div\u003e  \u003cbr\u003e ","value":{"A":"孩子们学习太紧张","B":"家长自己就不读书","C":"孩子们没找到好书","D":"大人的方法有问题"}},{"number":"9","header":"9. 关于刘可心的孩子，下列哪项正确？\n\u003caudio controls\u003d\"\" controlsList\u003d\"nodownload\"\u003e \r\n  \u003csource src\u003d\"http://localhost:8081/audios/BT/6/05 - Giáo trình chuẩn HSK 6 - SBT - question 8.mp3\" type\u003d\"audio/mpeg\"\u003e Your browser does not support the audio element. \r\n \u003c/audio\u003e \u003cdiv class\u003d\"btn-slide\"\u003e   \u003cdiv class\u003d\"btn\" style\u003d\"    background-color: inherit;    padding-top: 0px;    \"\u003e \u003cspan onclick\u003d\"previous(this)\" type\u003d\"button\"\u003e\u003ci class\u003d\"fa fa-backward\" style\u003d\"    color: black;\"\u003e\u003c/i\u003e\u003c/span\u003e   \u003c/div\u003e   \u003cdiv class\u003d\"btn\" style\u003d\"    background-color: inherit;    padding-right: 30px;    padding-top: 0px;    padding-bottom: 10px;    padding-left: 30px;    \"\u003e \u003cspan onclick\u003d\"next(this)\" type\u003d\"button\"\u003e\u003ci class\u003d\"fa fa-forward\" style\u003d\"    color: black;\"\u003e\u003c/i\u003e\u003c/span\u003e   \u003c/div\u003e  \u003c/div\u003e  \u003cbr\u003e ","value":{"A":"读书使他喜次上了历史","B":"每本书他都会认真读完","C":"每部小说他都会反复看","D":"父亲喜改武侠他也喜欢"}},{"number":"10","header":"10.对“读万卷书行万里路”，刘可心怎么看？\u003caudio controls\u003d\"\" controlsList\u003d\"nodownload\"\u003e \r\n  \u003csource src\u003d\"http://localhost:8081/audios/BT/6/05 - Giáo trình chuẩn HSK 6 - SBT - question 9.mp3\" type\u003d\"audio/mpeg\"\u003e Your browser does not support the audio element. \r\n \u003c/audio\u003e \u003cdiv class\u003d\"btn-slide\"\u003e   \u003cdiv class\u003d\"btn\" style\u003d\"    background-color: inherit;    padding-top: 0px;    \"\u003e \u003cspan onclick\u003d\"previous(this)\" type\u003d\"button\"\u003e\u003ci class\u003d\"fa fa-backward\" style\u003d\"    color: black;\"\u003e\u003c/i\u003e\u003c/span\u003e   \u003c/div\u003e   \u003cdiv class\u003d\"btn\" style\u003d\"    background-color: inherit;    padding-right: 30px;    padding-top: 0px;    padding-bottom: 10px;    padding-left: 30px;    \"\u003e \u003cspan onclick\u003d\"next(this)\" type\u003d\"button\"\u003e\u003ci class\u003d\"fa fa-forward\" style\u003d\"    color: black;\"\u003e\u003c/i\u003e\u003c/span\u003e   \u003c/div\u003e  \u003c/div\u003e  \u003cbr\u003e ","value":{"A":"书当做是读得越多越好","B":"行万里路一点儿后都没有","C":"读书不在多少，关键是用心","D":"天天忙着旅游和没法读书了"}}],"category":"NGHE"},{"type":"2","number":"11-13","header":"我们常常会听到家长感叹，现在的孩子，能安安静静坐下来看书的实在太少。想想我们小的时候，一本书在同学之间传来传去，大家迫不及待地轮流传阅，兴致勃勃地捧着一本书，如痴如醉……那样的乐趣，我们的孩子为什么就完全没有感觉呢？\n王先生常抱怨，儿子小的时候，自己每天晚上给他读故事，本以为他长大了， 在读书方面，会成为自己的知音。现实却并非如此，儿子对老师推荐的书、家长给他买的书好像都没兴致，偶尔翻看一下，不过是应付老师和家长。\n在浮躁的现代生活氛围中，借助互联网和各色电子产品，人们可以接触到最新娱乐资讯，可以在卡通动漫和电脑游戏中得到放松。人们将大量时间耗费在手机、电脑与电视机前。因此，如何让心灵回归沉静，已经成为摆在人们面前的难题。\n","body":[{"number":"11","header":"11.家长常为什么事感叹？\n","value":{"A":"孩子们安静不下来","B":"孩子们不喜欢看书","C":"自己小时候没有书看","D":"自己小时候没钱买书"}},{"number":"12","header":"12.王先生常抱怨什么？\n\u003caudio controls\u003d\"\" controlsList\u003d\"nodownload\"\u003e \r\n  \u003csource src\u003d\"http://localhost:8081/audios/BT/6/05 - Giáo trình chuẩn HSK 6 - SBT - question 11.mp3\" type\u003d\"audio/mpeg\"\u003e Your browser does not support the audio element. \r\n \u003c/audio\u003e \u003cdiv class\u003d\"btn-slide\"\u003e   \u003cdiv class\u003d\"btn\" style\u003d\"    background-color: inherit;    padding-top: 0px;    \"\u003e \u003cspan onclick\u003d\"previous(this)\" type\u003d\"button\"\u003e\u003ci class\u003d\"fa fa-backward\" style\u003d\"    color: black;\"\u003e\u003c/i\u003e\u003c/span\u003e   \u003c/div\u003e   \u003cdiv class\u003d\"btn\" style\u003d\"    background-color: inherit;    padding-right: 30px;    padding-top: 0px;    padding-bottom: 10px;    padding-left: 30px;    \"\u003e \u003cspan onclick\u003d\"next(this)\" type\u003d\"button\"\u003e\u003ci class\u003d\"fa fa-forward\" style\u003d\"    color: black;\"\u003e\u003c/i\u003e\u003c/span\u003e   \u003c/div\u003e  \u003c/div\u003e  \u003cbr\u003e ","value":{"A":"儿子对自已很反感","B":"儿子长大了，不听话了","C":"儿子长大后并不爱读书","D":"现在的老师不为学生着想"}},{"number":"13","header":"13.如今摆在人们面前的难题是什么？\u003caudio controls\u003d\"\" controlsList\u003d\"nodownload\"\u003e \r\n  \u003csource src\u003d\"http://localhost:8081/audios/BT/6/05 - Giáo trình chuẩn HSK 6 - SBT - question 12.mp3\" type\u003d\"audio/mpeg\"\u003e Your browser does not support the audio element. \r\n \u003c/audio\u003e \u003cdiv class\u003d\"btn-slide\"\u003e   \u003cdiv class\u003d\"btn\" style\u003d\"    background-color: inherit;    padding-top: 0px;    \"\u003e \u003cspan onclick\u003d\"previous(this)\" type\u003d\"button\"\u003e\u003ci class\u003d\"fa fa-backward\" style\u003d\"    color: black;\"\u003e\u003c/i\u003e\u003c/span\u003e   \u003c/div\u003e   \u003cdiv class\u003d\"btn\" style\u003d\"    background-color: inherit;    padding-right: 30px;    padding-top: 0px;    padding-bottom: 10px;    padding-left: 30px;    \"\u003e \u003cspan onclick\u003d\"next(this)\" type\u003d\"button\"\u003e\u003ci class\u003d\"fa fa-forward\" style\u003d\"    color: black;\"\u003e\u003c/i\u003e\u003c/span\u003e   \u003c/div\u003e  \u003c/div\u003e  \u003cbr\u003e ","value":{"A":"怎样远离电脑游戏","B":"怎样让心灵安静下来","C":"怎样克服互联网的弊端","D":"如何让娱乐资讯有深度"}}],"category":"NGHE"},{"type":"2","number":"14-17","header":"有人说学好外语就得努力学、拼命学，得有大把的时间，我却说学外语就得“见缝插针”。所谓“见缝插针”，就是要把一般人看着不起眼的零碎时间都利用起来。可千万别看不起这几分钟十几分钟的时间，根据记忆心理学的原理，对于外语等以机械记忆为主的学习内容，及时地利用零碎时间进行复习，效果是很好的，学了就搁在一边，等于没学。\n “见缝插针”的另一种方式就是把外语学习和日常生活联系起来，处处学，时时学，事事学。只要有了学习外语的强烈愿望和兴趣，日常生活的各个方面都可以成为外语学习的第二课堂，而且在日常生活中学到的外语记得快、记得牢，学习效果特别好。\n“见缝插针”时间长了，就会感到外语学习已成为自己生活中不可缺少的内容，就会感到学习外语是一种乐趣和享受，一天不学就好像缺了点儿什么。\n","body":[{"number":"14","header":"14.怎样“见缝插针”学外语？\n\u003caudio controls\u003d\"\" controlsList\u003d\"nodownload\"\u003e \r\n  \u003csource src\u003d\"http://localhost:8081/audios/BT/6/05 - Giáo trình chuẩn HSK 6 - SBT - question 13.mp3\" type\u003d\"audio/mpeg\"\u003e Your browser does not support the audio element. \r\n \u003c/audio\u003e \u003cdiv class\u003d\"btn-slide\"\u003e   \u003cdiv class\u003d\"btn\" style\u003d\"    background-color: inherit;    padding-top: 0px;    \"\u003e \u003cspan onclick\u003d\"previous(this)\" type\u003d\"button\"\u003e\u003ci class\u003d\"fa fa-backward\" style\u003d\"    color: black;\"\u003e\u003c/i\u003e\u003c/span\u003e   \u003c/div\u003e   \u003cdiv class\u003d\"btn\" style\u003d\"    background-color: inherit;    padding-right: 30px;    padding-top: 0px;    padding-bottom: 10px;    padding-left: 30px;    \"\u003e \u003cspan onclick\u003d\"next(this)\" type\u003d\"button\"\u003e\u003ci class\u003d\"fa fa-forward\" style\u003d\"    color: black;\"\u003e\u003c/i\u003e\u003c/span\u003e   \u003c/div\u003e  \u003c/div\u003e  \u003cbr\u003e ","value":{"A":"工作给别人，自己学外语","B":"有了充足的时间再学外语","C":"别人看电视时自己学外语","D":"多么短的时间都利用起来"}},{"number":"15","header":"15.“见缝插针”学外语的好处是什么？\n\u003caudio controls\u003d\"\" controlsList\u003d\"nodownload\"\u003e \r\n  \u003csource src\u003d\"http://localhost:8081/audios/BT/6/05 - Giáo trình chuẩn HSK 6 - SBT - question 14.mp3\" type\u003d\"audio/mpeg\"\u003e Your browser does not support the audio element. \r\n \u003c/audio\u003e \u003cdiv class\u003d\"btn-slide\"\u003e   \u003cdiv class\u003d\"btn\" style\u003d\"    background-color: inherit;    padding-top: 0px;    \"\u003e \u003cspan onclick\u003d\"previous(this)\" type\u003d\"button\"\u003e\u003ci class\u003d\"fa fa-backward\" style\u003d\"    color: black;\"\u003e\u003c/i\u003e\u003c/span\u003e   \u003c/div\u003e   \u003cdiv class\u003d\"btn\" style\u003d\"    background-color: inherit;    padding-right: 30px;    padding-top: 0px;    padding-bottom: 10px;    padding-left: 30px;    \"\u003e \u003cspan onclick\u003d\"next(this)\" type\u003d\"button\"\u003e\u003ci class\u003d\"fa fa-forward\" style\u003d\"    color: black;\"\u003e\u003c/i\u003e\u003c/span\u003e   \u003c/div\u003e  \u003c/div\u003e  \u003cbr\u003e ","value":{"A":"有新鲜感","B":"有成就感","C":"有利于记忆","D":"不浪费时间"}},{"number":"16","header":"16.“见缝插针”的另一种学习方式是什么？\n\u003caudio controls\u003d\"\" controlsList\u003d\"nodownload\"\u003e \r\n  \u003csource src\u003d\"http://localhost:8081/audios/BT/6/05 - Giáo trình chuẩn HSK 6 - SBT - question 15.mp3\" type\u003d\"audio/mpeg\"\u003e Your browser does not support the audio element. \r\n \u003c/audio\u003e \u003cdiv class\u003d\"btn-slide\"\u003e   \u003cdiv class\u003d\"btn\" style\u003d\"    background-color: inherit;    padding-top: 0px;    \"\u003e \u003cspan onclick\u003d\"previous(this)\" type\u003d\"button\"\u003e\u003ci class\u003d\"fa fa-backward\" style\u003d\"    color: black;\"\u003e\u003c/i\u003e\u003c/span\u003e   \u003c/div\u003e   \u003cdiv class\u003d\"btn\" style\u003d\"    background-color: inherit;    padding-right: 30px;    padding-top: 0px;    padding-bottom: 10px;    padding-left: 30px;    \"\u003e \u003cspan onclick\u003d\"next(this)\" type\u003d\"button\"\u003e\u003ci class\u003d\"fa fa-forward\" style\u003d\"    color: black;\"\u003e\u003c/i\u003e\u003c/span\u003e   \u003c/div\u003e  \u003c/div\u003e  \u003cbr\u003e ","value":{"A":"在目常生活中学习","B":"培养学外语的兴趣","C":"锻炼自已的亿力","D":"和外国人多多接触"}},{"number":"17","header":"17.这段话告诉我们什么？\u003caudio controls\u003d\"\" controlsList\u003d\"nodownload\"\u003e \r\n  \u003csource src\u003d\"http://localhost:8081/audios/BT/6/05 - Giáo trình chuẩn HSK 6 - SBT - question 16.mp3\" type\u003d\"audio/mpeg\"\u003e Your browser does not support the audio element. \r\n \u003c/audio\u003e \u003cdiv class\u003d\"btn-slide\"\u003e   \u003cdiv class\u003d\"btn\" style\u003d\"    background-color: inherit;    padding-top: 0px;    \"\u003e \u003cspan onclick\u003d\"previous(this)\" type\u003d\"button\"\u003e\u003ci class\u003d\"fa fa-backward\" style\u003d\"    color: black;\"\u003e\u003c/i\u003e\u003c/span\u003e   \u003c/div\u003e   \u003cdiv class\u003d\"btn\" style\u003d\"    background-color: inherit;    padding-right: 30px;    padding-top: 0px;    padding-bottom: 10px;    padding-left: 30px;    \"\u003e \u003cspan onclick\u003d\"next(this)\" type\u003d\"button\"\u003e\u003ci class\u003d\"fa fa-forward\" style\u003d\"    color: black;\"\u003e\u003c/i\u003e\u003c/span\u003e   \u003c/div\u003e  \u003c/div\u003e  \u003cbr\u003e ","value":{"A":"工作忙不是学不好外语的借口","B":"学习外语的过程也是一种享爱","C":"只要有时间就不会学不好外语","D":"会“见缝插针”的人都能成功"}}],"category":"NGHE"},{"type":"3","number":"18","header":"\u003cdiv class\u003d\"qustion\"\u003e\u003cdiv class\u003d\"field-number\"\u003e  1 \u003c/div\u003e \u003cdiv class\u003d\"field-image\"\u003e  \u003cimg src\u003d\"!image_source!\" alt\u003d\"\"\u003e \u003c/div\u003e \u003cdiv class\u003d\"field-audio\"\u003e   \u003c/div\u003e \u003cdiv class\u003d\"text-center field-subject ans-hide\"\u003e  \u003cp class\u003d\"pinyin\"\u003e\u003c/p\u003e \u003c/div\u003e\u003c/div\u003e","body":[{"number":"18","value":{"A":"一切成功的教有必须基于爱，借助于爱，归结于爱。","B":"一个用心温暖别人的人，她自已的心也必然是温暖的。","C":"他的父亲。爷爷都是书法家，书法作品对他一点儿也不陌生。","D":"夕阳西下，我看到她正坐在门口专注地倾听着什么，脸上有种奇异的微笑"}}],"category":"DOC_HIEU"},{"type":"3","number":"19","header":"\u003cdiv class\u003d\"qustion\"\u003e\u003cdiv class\u003d\"field-number\"\u003e  1 \u003c/div\u003e \u003cdiv class\u003d\"field-image\"\u003e  \u003cimg src\u003d\"!image_source!\" alt\u003d\"\"\u003e \u003c/div\u003e \u003cdiv class\u003d\"field-audio\"\u003e   \u003c/div\u003e \u003cdiv class\u003d\"text-center field-subject ans-hide\"\u003e  \u003cp class\u003d\"pinyin\"\u003e\u003c/p\u003e \u003c/div\u003e\u003c/div\u003e","body":[{"number":"19","value":{"A":"听家望人说他是春节以后找到工作了。","B":"这是一本值得一辈子去学习，去研究，去实践的好书","C":"妈妈年轻的时候有一个最奢侈的梦想，就是拥有一辆新自行车。","D":"春天，万物复苏，小草从土里悄悄地探出头来，好奇地四处张望"}}],"category":"DOC_HIEU"},{"type":"3","number":"20","header":"\u003cdiv class\u003d\"qustion\"\u003e\u003cdiv class\u003d\"field-number\"\u003e  1 \u003c/div\u003e \u003cdiv class\u003d\"field-image\"\u003e  \u003cimg src\u003d\"!image_source!\" alt\u003d\"\"\u003e \u003c/div\u003e \u003cdiv class\u003d\"field-audio\"\u003e   \u003c/div\u003e \u003cdiv class\u003d\"text-center field-subject ans-hide\"\u003e  \u003cp class\u003d\"pinyin\"\u003e\u003c/p\u003e \u003c/div\u003e\u003c/div\u003e","body":[{"number":"20","value":{"A":"世界各国民航部门都对商业无人机的滥用挖头不已。","B":"我的家乡物产丰富，风景秀丽，被人们称为“草原明殊”。","C":"他比过去成熟了，知道身体健博的重要性，更懂得约束自已。","D":"念大学的时候，我常跟朋友去游冰，其实我并不喜欢游泳，只是凑个热闹"}}],"category":"DOC_HIEU"},{"type":"3","number":"21","header":"\u003cdiv class\u003d\"qustion\"\u003e\u003cdiv class\u003d\"field-number\"\u003e  1 \u003c/div\u003e \u003cdiv class\u003d\"field-image\"\u003e  \u003cimg src\u003d\"!image_source!\" alt\u003d\"\"\u003e \u003c/div\u003e \u003cdiv class\u003d\"field-audio\"\u003e   \u003c/div\u003e \u003cdiv class\u003d\"text-center field-subject ans-hide\"\u003e  \u003cp class\u003d\"pinyin\"\u003e她的教育人生、如果用一个字来________，那就是“爱”。有了“爱”，她就有了无限的精力、无限的________，无限的事业________。\u003c/p\u003e \u003c/div\u003e\u003c/div\u003e","body":[{"number":"21","value":{"A":"总结     本领     动能","B":"概述     技能     能量","C":"概括     才能     动力","D":"包括     才华     能力"}}],"category":"DOC_HIEU"},{"type":"3","number":"22","header":"\u003cdiv class\u003d\"qustion\"\u003e\u003cdiv class\u003d\"field-number\"\u003e  1 \u003c/div\u003e \u003cdiv class\u003d\"field-image\"\u003e  \u003cimg src\u003d\"!image_source!\" alt\u003d\"\"\u003e \u003c/div\u003e \u003cdiv class\u003d\"field-audio\"\u003e   \u003c/div\u003e \u003cdiv class\u003d\"text-center field-subject ans-hide\"\u003e  \u003cp class\u003d\"pinyin\"\u003e幸福是什么?________很重要，但仅仅“够用”就可以了。北欧人的幸福感。更多米源于简约、自然、平和的________以及家庭的温暖、个人的________，而这些是我们可以学会、可以身体力行的，也是我们自古以来________倡导的。\u003c/p\u003e \u003c/div\u003e\u003c/div\u003e","body":[{"number":"22","value":{"A":"物质     心态     努力     一直","B":"物资     心里     勤劳     从来","C":"东西     想法     奋斗     不停","D":"财务     态度     尽力     不断"}}],"category":"DOC_HIEU"},{"type":"3","number":"23","header":"\u003cdiv class\u003d\"qustion\"\u003e\u003cdiv class\u003d\"field-number\"\u003e  1 \u003c/div\u003e \u003cdiv class\u003d\"field-image\"\u003e  \u003cimg src\u003d\"!image_source!\" alt\u003d\"\"\u003e \u003c/div\u003e \u003cdiv class\u003d\"field-audio\"\u003e   \u003c/div\u003e \u003cdiv class\u003d\"text-center field-subject ans-hide\"\u003e  \u003cp class\u003d\"pinyin\"\u003e中华鲟是古老的________鱼类，现今仅在中国长江流域________有分布。曾有外国人希望将它________到自己的国度安家落户，但中华鲟总要洄游到故乡的江河生儿育女女、所以人们给它________“中华”二字。\u003c/p\u003e \u003c/div\u003e\u003c/div\u003e","body":[{"number":"23","value":{"A":"珍视     且     转移     加上","B":"珍稀     尚     引进     冠以","C":"珍重     仍     搬家     命名","D":"爱惜     犹     移民     起名"}}],"category":"DOC_HIEU"},{"type":"6","number":"24-28","header":"2400多年前，有个叫曾子的人，他16岁拜孔子为师，勤奋好学，（24）\u003cspan class\u003d\"child-number\" data-child\u003d\"31604\" id\u003d\"24\" onclick\u003d\"chooseQuestion(24)\" style\u003d\"cursor: pointer;border-bottom: 1px solid #39a0ff;color:red\" selected\u003d\"false\"\u003e___\u003cspan class\u003d\"child-select rev-hide\"\u003e\u003c/span\u003e\u003c/span\u003e。\n曾子不仅有学问，（25）\u003cspan class\u003d\"child-number\" data-child\u003d\"31604\" id\u003d\"25\" onclick\u003d\"chooseQuestion(25)\" style\u003d\"cursor: pointer;border-bottom: 1px solid #39a0ff;color:red\" selected\u003d\"false\"\u003e___\u003cspan class\u003d\"child-select rev-hide\"\u003e\u003c/span\u003e\u003c/span\u003e，即使对孩子，也是一样。一次，曾子的妻子要到街上去买东西，儿子哭闹着要跟着去。妻子对儿子说，（26）\u003cspan class\u003d\"child-number\" data-child\u003d\"31604\" id\u003d\"26\" onclick\u003d\"chooseQuestion(26)\" style\u003d\"cursor: pointer;border-bottom: 1px solid #39a0ff;color:red\" selected\u003d\"false\"\u003e___\u003cspan class\u003d\"child-select rev-hide\"\u003e\u003c/span\u003e\u003c/span\u003e，好好待在家里，回来就杀猪给他炖肉吃。孩子以为母亲说的是真的，就不闹了，在家里安安静静地等着。\n妻子买东西回来，一进门就看到曾子已经拿出了刀，做着杀猪的准备。妻子吓了一跳，赶忙说：“你真的要杀猪吗?我没跟他说实话，（27）\u003cspan class\u003d\"child-number\" data-child\u003d\"31604\" id\u003d\"27\" onclick\u003d\"chooseQuestion(27)\" style\u003d\"cursor: pointer;border-bottom: 1px solid #39a0ff;color:red\" selected\u003d\"false\"\u003e___\u003cspan class\u003d\"child-select rev-hide\"\u003e\u003c/span\u003e\u003c/span\u003e，我没真想把家里的猪杀了呀。”曾子认真地说：“我们的行为会影响孩子，如果我们说话不算数，（28）\u003cspan class\u003d\"child-number\" data-child\u003d\"31604\" id\u003d\"28\" onclick\u003d\"chooseQuestion(28)\" style\u003d\"cursor: pointer;border-bottom: 1px solid #39a0ff;color:red\" selected\u003d\"false\"\u003e___\u003cspan class\u003d\"child-select rev-hide\"\u003e\u003c/span\u003e\u003c/span\u003e，我们就会把孩子教育成不诚实的人。”妻子听了曾子的话，觉得有道理，于是，帮着丈夫把猪杀了，做了一顿丰盛的晚餐。","body":[{"number":"24-28","value":{"A":"做人诚实也是出了名的","B":"无非是为了哄孩子不要哭闹","C":"是春秋时期的著名学者","D":"孩子会跟我们学","E":"只要他不闹"}}],"category":"DOC_HIEU"},{"type":"2","number":"29-32","header":"精通古汉语，对外文完全是门外汉的林纾是中国著名翻译家。近代文学翻译的开创者.，正式译介西方文学的第一人。他以“耳受笔追”的方式，与留洋学子合作，翻译了11个国家107创作家的作品，对引进西方文学和促进中国社会文化的进步做出了巨大贡献。\n林纾有个朋友叫王昌寿，曾赴法留学 6 年，精通法语。他常给林纾讲外国名著，每次林纾都听得津津有味。一来二去林纾喜欢上了西方文学，并产生了将其翻译给国人的念头。林纾想虽然自己看不懂外文，可是搭上王昌寿，俩人就没啥做不成的。于是二人达成协议，合作翻译法国名著《茶花女》，办法是王昌寿口译，林纾记录并成文。那时，人们常看到这样一幅景致：王昌寿面前搁着本原著，边浏览，边口述；林纾耳聪手疾，文思如泉涌，经常是王昌寿说完一句的同时，林纾就已经挥笔成文了。半天下来，两人能译出6000多字。1899年夏天，中国首部翻译小说《巴黎茶花女遗事》公开发售。一时间，阅访翻泽小说成了社会风尚，众人争相抢阅。此后的27年里，林纾与魏易、陈家麟等留学归来的才子合作翻译了160余部外国名著，这些小说向中国民众展示了丰富的西方文化，开阔了人们的视野。\n除翻译外，林纾还是一位深受读者欢迎的作家，他接连发表的长篇小说和一系列短篇小说生动地反映了当时的社会现实，深受读者喜爱。此外，林纾还是一位不错的画家，他23岁拜师学画，绘画成就不亚于文学创作和翻译。","body":[{"number":"29","header":"根据第1段可以知道，林纾：","value":{"A":"一点儿外语也不会","B":"把古汉语翻译成了外文","C":"曾经去过十多个国家","D":"促进了西方文学的发展"}},{"number":"30","header":"根据第2段可以知道：","value":{"A":"《茶花女》是林纾，王昌寿合写的","B":"1899年中国出版了第一本翻译小说","C":"《巴黎茶花女遗事》一出版就被抢光","D":"1899年之后，中国出了很多翻译家"}},{"number":"31","header":"第2段画线词语“耳聪手疾”的意思是：","value":{"A":"手有问题了","B":"耳朵听不见了","C":"耳朵很好手不行","D":"耳朵也好手也快"}},{"number":"32","header":"通过最后一段我们还知道，林纾：","value":{"A":"尊重每一位读者","B":"喜欢看各类小说","C":"23岁时教过画画儿","D":"画画儿不比写作差"}}],"category":"DOC_HIEU"},{"type":"2","number":"33-36","header":"不少工作繁忙、不希望把学习过程拖得太长的中国人，都希望能在短时间内学会英语。有人提出过这样的间题，“英语速成”可能吗？\n如果我斩钉截铁地告诉你，到现在为止没有例子能够证明在一年之内可以做到听说读写没问题，请你不要失望。因为对于中国人来说，英语是一门外语，从什么都不会到能够听、说、读、写，是一个必须按照学习规律一步一个脚印走过的过程，期间没有近路可走。\n如果止我为你策划学习方式，我想告诉你，学英语首先要以最严格的要求，从基础知识抓起，要学好每一个词、每一句话，之后再谈提高和强化。学习中要先把课本知识学好，把课本内容掌握得滚瓜烂熟之后，再去光顾课外材料，这种看起来在基础知识上耽误了时间的笨方法，倒有可能使你收到事半功倍的效果。\n其次，不要把心思放在应试技巧上，梦想依靠所谓技巧在短期内通过某种考试。虽然一些技巧对某些人的命运能够起到决定性作用，但离开考场以后，所谓的技巧却没有任何实际应用价值。学习英语的根本目的在于应用，因此学习英语的每一个环节都应着眼于实际能力的培养与提高。\n另外，一种很好的学习方法就是“听写录音”，把你听到的英语记录下来，可以让你清楚，你什么地方听不懂、写不出，让你直观地感受到你的不足在哪里，你也就找到了正的出发点。经过努力，就能听懂了、写对了，你取得的进步也是实实在在的。如此这般，英语水平自然会日渐提高，最后顺利到达终点。","body":[{"number":"33","header":"什么样的人希望学习“速成英语”?","value":{"A":"自认为聪明过人的人","B":"做事随意不善计划的人","C":"了解外语学习规律的人","D":"想在短时间学会英语的人"}},{"number":"34","header":"学英环最重要的方法是什么?","value":{"A":"记住单词","B":"背诵句子","C":"打好基础","D":"看课外书"}},{"number":"35","header":"关于应试技巧，作者认为：","value":{"A":"掌握应试技巧很重要","B":"学应试技巧很费时间","C":"靠应试技巧学不好英语","D":"应试技巧在生活中有用"}},{"number":"36","header":"作者队为一种很好的学习方法是什么?","value":{"A":"边听录音边写下听到的英语","B":"反复听录音中听不懂的地方","C":"善于发现自已学习中的弱点","D":"每天都能感受到自已的进步"}}],"category":"DOC_HIEU"}]