{"title":"亲近自然","lessionParts":[{"part":"36","location":"老舍与养花","description":"作家老舍先生爱花，他养的花很多，满满摆了一院子。可除非是那些好种易活、自己会奋斗的花草，否则他是不养的。因为他知道北京的气候对养花来说，不算很好，想把南方的名花养活并非易事。\u003cbr/\u003e\u003cbr/\u003e老舍把养花当作一种生活乐趣。他不在乎花开得大小好坏，只要开花，他就高兴。每天老舍像好朋友似的照管着花草。工作的时候，经常写几十个字，就到院中去转转，瞧瞧这棵，看看那朵，有时拿起剪刀给它们剪剪枝，有时蹲下捡几块小石头放在花盆里做点儿装饰，然后回到屋中再写一会儿，然后再出去，就这样脑力和体力很好地结合，身心也得到放松。\u003cbr/\u003e\u003cbr/\u003e写作是件艰苦的工作，养花也是如此。有时赶上狂风暴雨，情况紧急，他就得劳驾全家人抢救花草。几百盆花，要很快地抢到屋里去，累得腰酸腿疼，热汗直流。第二天，天气好了，又得一盆盆地搬出去。可是，他并不抱怨，在他看来，任何事都要有付出，不然怎么会有回报?这是生活的真理。\u003cbr/\u003e\u003cbr/\u003e\u003cstrong\u003e一来二去，他慢慢地总结出一些养花的经验\u003c/strong\u003e：有的花喜干，就别多浇水；有的花喜欢潮湿的环境，就别放在太阳地里。给花换盆剪枝施肥的活儿他越做越熟练，花生病长虫他也知道如何应付了。看着院子里那鲜艳的花朵，老舍自豪地说，“不是乱吹，这就是知识啊！多得些知识，一定不是坏事。”\u003cbr/\u003e\u003cbr/\u003e老舍很有爱心，更懂得快乐要分享。每到县花开放的时候，他就约上几位朋友来家里赏花庆祝。花分根了，一棵分为几棵，他会毫无保留地送给朋友们。看着友人高兴地拿走自己的劳动果实，老舍心里十分欢喜。有一次，送牛奶的小伙子进门就夸“好香”！这让老舍先生感到格外高兴。\u003cbr/\u003e\u003cbr/\u003e当然，也有伤心的时候。一年夏天，下了暴雨，邻居家的墙倒了，菊花被砸死了一百多棵，这下可把老舍难受坏了，一连几天人们都看不到他脸上的笑容。\u003cbr/\u003e\u003cbr/\u003e“有喜有悲，有笑有泪”，这是老舍对养花、对生活的体验。“我不知道花草们受我的照顾，感谢我不感谢，反正我要感谢它们。”老舍在自己的文章中这样写道。从中我们不难看出老舍先生对大自然的热爱，对生活的热爱。"}]}